{
 "מִמֲֶָּ": "from-what?",
 "אַפּוֹטְרוֹפְּסִים": "guardian(pl)",
 "לְהִתְאַרְגֵּן": "to-to become organized",
 "בְּנִהוּל": "in-management",
 "הֻסְמְכוּ": "they will lay",
 "חֲסִידוּת": "Hassidism",
 "הֻסְמַךְ": "to be authorized",
 "לְסַיֵּעַ": "to-assistant",
 "הִשְׁתַּדֵּל": "to make efforts",
 "הוֹשַׁעְנָא": "a willow branch beaten on the grou",
 "יִנָּטְעוּ": "he-will-they have been planted",
 "נְאֻמִי": "we-will-mother-my",
 "הָאֱלֹהוּת": "the-divinity",
 "הִתְנַצְּלוּת": "apology",
 "נְכַלֶּה": "we-will-completion",
 "נְיוּאֵל": "we-will-Joel (Hebrew name)",
 "אַחֲרָיוּת": "responsibility",
 "הָרִשֻּׁמוֹת": "registration",
 "רִשְׁמֵי": "official",
 "שִׁירֵי": "poetic",
 "וּלְהִכָּנֵס": "and-to-to be inserted",
 "הִתְנַשְּׂאוּתָם": "arrogance-them",
 "נִמְשֶׁכֶת": "we-will-you will march",
 "בַּמַּאֲסָר": "in-the-imprisonment",
 "תִּסָּמֵךְ": "you/she-will-to depend on",
 "נִסְמַךְ": "to be based on",
 "יְצַפֶּה": "he-will-to watch",
 "בְּכֵנוּת": "in-frankness",
 "מוֹרְלִי": "morale-my",
 "שְׁלִיחוּתָם": "mission-them",
 "בְּטָעוּת": "in-mistake",
 "שׁוּשֶׁלֶת": "dynasty",
 "הוּשַׁת": "to be imposed",
 "נֶאֱהַב": "to be loved",
 "אַל־תְּשַׁלְּמוּ": "Don't!-you/she-will-repay",
 "הַפְּסוּלִים": "the-invalid(pl)",
 "וּבַחֲסִידוּת": "and-in-the-Hassidism",
 "הַמִּתְקוֹמֵם": "the-insurrectionist",
 "נִבּוּל": "withered",
 "בְּשַׁעַת": "during",
 "נִמְנוֹת": "we-will-count",
 "מִן־הַמְסֻבִּים": "from-the-around",
 "מוֹכֵס": "customs official",
 "נֶהֱנֶה": "beneficiary",
 "יְוָנִית": "Greek (language)",
 "קֵיסַרְיָה": "imperial",
 "טֹעִים": "tasty",
 "טַלִּית": "prayer shawl",
 "מַרְגָּלִית": "gem",
 "נִתְמַלֵּא": "we-will-may you fill",
 "מָסוּךְ": "shielding",
 "מַה־בְּכָךְ": "what?-in-like this",
 "אֶת־גְּוִיּוֹתֵיכֶם": "term used to indicate a direct object-gentile-your(pl)",
 "סַכָּנָה": "danger",
 "נִתְהַלְּכָה": "we-will-procession",
 "זְרִיזוּת": "nimbleness",
 "לַעֲרוֹב": "to-the-a swarm of wild beasts (the fourth of the ten plag",
 "אֶל־אֵילָו": "at-strength",
 "לְהִשָּׂרֵף": "to-he burned",
 "לְהִקָּנוֹת": "to-buy",
 "לְהִכּוֹנֵן": "to-to establish",
 "מִנּוּיֵיהֶם": "from-beauty-their",
 "מִנּוּי": "appointing",
 "וּבֵינוֹנַי": "and-medium",
 "בְּחַמְדָנוּת": "in-greediness",
 "וְהַסְכָּמָה": "and-the-schema",
 "הַכְּלָלִית": "the-in general",
 "אַפּוֹטְרוֹפּוֹס": "guardian",
 "בְּכָל־הַמִּשְׂרוֹת": "among-all-the-from-the chief of(pl)",
 "הַחְלָטוֹתֵיהֶם": "the-to blanch-their",
 "זַכָּאִיוֹת": "innocent(pl)",
 "וּלְסַדֵּר": "and-to-order",
 "בְּכָל־הָאֻמּוֹת": "among-all-the-tribes",
 "לְסִיּוּעַ": "to-aid",
 "לְהַסְמִיךְ": "to-the-thick (soup, gravy, hair, fog)",
 "נִהוּל": "management",
 "זוֹהִי": "this is",
 "זָהִיר": "careful",
 "הֵחָתֵם": "to be signed",
 "נְשׂוּאוֹת": "one uplifted of(pl)",
 "הִתְכַּוֵּן": "to intend",
 "נִיוּאֵל": "we-will-Joel (Hebrew name)",
 "בְּוַדַּאי": "in-certainty",
 "תַּעֲזֹר": "you/she-will-to help",
 "תַּעַמְלוּ": "you/she-will-mischief-his",
 "אֶת־כָּל־חוֹבוֹת": "term used to indicate a direct object-every-debt(pl)",
 "יְטֻפַּל": "he-will-to frame",
 "הָאוּז": "the-goose",
 "יְיַעֲדוּ": "he-will-he had appointed for-him",
 "פוֹסְטֶר": "poster",
 "הַפְּקִידוּת": "the-clerical work",
 "בִּטְחוֹנִי": "security",
 "עִמָּנוּאֵל": "Emanuel",
 "אֲסַיֵּם": "I-will-to finish",
 "וְהֶמְשֵׁךְ": "and-continuation",
 "הִתְנַשְּׂאוּתוֹ": "arrogance-his",
 "תִּסְלַח": "you/she-will-forgive",
 "לְהַעֲנִישׁ": "to-to punish",
 "לְהַסְדִּיר": "to-the-regular",
 "הַצְּלִיבָה": "the-crucifixion",
 "יְתַרְגֵּם": "he-will-translate",
 "אוֹהָיוֹ": "Ohio",
 "שׁוֹלְטִים": "dominant(pl)",
 "זוּגָם": "pair-them",
 "חֲקִירָה": "investigation",
 "יִנָּזֵף": "he-will-to reproach",
 "שׁוֹאֵל": "questioner",
 "יִרְכֹּשׁ": "he-will-the possessions of",
 "יִזָּהֵר": "Yizhar (Hebrew name)",
 "וְהַנִּשְׁלָח": "and-the-to be sent",
 "יַעֲסֹק": "he-will-to deal with",
 "בּ": "in",
 "וּבִמְיֻחָד": "and-mainly",
 "לְהִכָּנֵס": "to-collect",
 "לְפַרְנֵס": "to-to support",
 "נוֹכְחוּת": "attendance",
 "וּלְהִתְקַבֵּל": "and-to-to be received",
 "כְּסוֹכֵן": "as-agent",
 "הַוְּעֵידָה": "the-conference",
 "תְּבֻטַּל": "you/she-will-desist from labor",
 "הַשְּׁלִיחוּת": "the-mission",
 "נוֹכְחוּתוֹ": "attendance-his",
 "מֻגְבָּלוֹת": "limited(pl)",
 "נִסְפָּחִים": "appendix(pl)",
 "לְהַרְהֵר": "to-to think about",
 "הִשְׁתַּמֵּשׁ": "to use",
 "אַל־תִּפָּרְדוּ": "Don't!-you/she-will-mule-his",
 "אֶת־יִצְרָם": "term used to indicate a direct object-to create-them",
 "לָהוּט": "enthusiastic",
 "וְעַל־הַנְּשׂוֹּאִים": "and-were from-the-certainly(pl)",
 "אַל־יְשַׁלְּחֶנָּה": "Don't!-he-will-table-her",
 "אִם־תּוֹשִׁיעִי": "if-you will deliver-my",
 "וְכֵן־מְתַקֵּן": "and-gnat-apparatus",
 "וְאֵין־הָעָרְלָה": "and-where?-the-foreskin",
 "מְשֻׁחֲרָר": "liberator",
 "אִם־זָקוּק": "if-in need of (ל)",
 "וְאִם־נִפְטַרְתָּ": "and-whether?-we-will-the firstborn of",
 "הֲנָאָה": "pleasure",
 "נִטְרָדִים": "to be worried(pl)",
 "פְנוּיָה": "vacant",
 "פְּנוּיָה": "vacant",
 "שְׁמוּעָתֵנוּ": "certainly if-our",
 "תוֹעַלְתִּי": "practicable",
 "הַזְּרִיעָה": "the-sowing",
 "נִישַׁן": "we-will-sleeping",
 "עִם־תַּאֲוֹתָיו": "with-the guardroom of-his",
 "הִבְטִיחָנוּ": "to promise-our",
 "פְּשִׁיעָה": "crime",
 "אֶת־חֲטָאֵינוּ": "term used to indicate a direct object-to sin-our",
 "נֶאֱהַב־נָא": "to be loved-please",
 "וְאִם־נֶאֱהַב": "and-whether?-to be loved",
 "נִשְׁכֹּן": "biting (child, dog, rodent)",
 "פֶּן־תִּכָּלְאוּ": "lest-you/she-will-they have withheld",
 "לְהַלְשִׁין": "to-to inform on",
 "נְקַדֵּם": "we-will-fore",
 "בְּכָל־חֲסִידוּת": "among-all-Hassidism",
 "הַסַּרְסוֹר": "the-pimp",
 "וּצְנִיעוּת": "and-modesty",
 "בְּכָל־הַכְנָעָה": "among-all-surrender",
 "תִּדּוֹם": "you/she-will-jujube (tree, fruit)",
 "עִם־הַצְּנִיעוּת": "with-the-modesty",
 "וְהֶגְמוֹן": "and-bishop",
 "וּמַדְרִיךְ": "and-guide",
 "פֶּן־יִרְהַב": "lest-he-will-importune",
 "וִכּוּחֵי": "argumentative",
 "נִשְׁחֲתֵי": "we-will-I am bent over",
 "הַמַּשְׁקִיעוֹת": "the-investor(pl)",
 "לְהוּטִים": "enthusiastic(pl)",
 "הוֹדָאָה": "confession",
 "הַהוֹדָאָה": "the-confession",
 "וְהִתְרַחֵק": "and-to move away from",
 "וּמִן־וִכּוּחֵי": "and-part-argumentative",
 "וּלְהָחִישׁ": "and-to-to speed up",
 "בְּכָל־אִגְּרוֹתָיו": "among-all-to accumulate-his",
 "פֶּן־תִּמָּשְׁכוּ": "lest-you/she-will-draw",
 "הַצָּע": "to be advised",
 "לְכָל־דִּקְדּוּקֶיהָ": "to-whole-grammar-her",
 "וְהִתְרַחֵץ": "and-to wash (oneself)",
 "לְהַלְקוֹת": "to-the-impairment",
 "הָאֶזְרָחוּת": "the-citizenship",
 "כָּל־הַסַּנְהֶדְרִין": "every-the-Sanhedrin (supreme judicial body during",
 "גְּנוּזִים": "hidden(pl)",
 "יַטְעֶה": "he-will-to make a mistake",
 "הָאֱלָהוּת": "the-divinity",
 "אַל־תִּטְעַם": "Don't!-you/she-will-to taste",
 "בְּכָל־נְמִיכוּת": "among-all-lowness",
 "נִגְרָשִׁים": "we-will-inverted commas",
 "הַשִּׁמּוּשׁ": "the-use",
 "לְהִתְחַדֵּשׁ": "to-you may renew",
 "עַל־רָגְזְכֶם": "super- (superhuman, supernatural)-to become angry-your(pl)",
 "הַמֵּפִיק": "the-producer",
 "פָּדָנוּ": "pad-our",
 "וּלְבַטֵּל": "and-to-desist from labor",
 "נִשְׁקְדָה־נָּא": "it has been bound on-please",
 "וּבֵין־הַמּוֹחַ": "and-between-the-brain",
 "לְהִצְטָעֵר": "to-to be sorry",
 "מֵהִתְחַדֵּשׁ": "from-to be renewed",
 "לְהִשָׂרֵף": "to-he burned",
 "בְּהִשְׁתַּנּוֹת": "in-changing",
 "וְקִצְרַת־יָד": "and-asthma-arm",
 "בְּמַה־שֶׁנְּצַפֶּה": "in-what?-that-to be seen",
 "לְהַזְרִיעַ": "to-to inseminate (animals)",
 "אֶת־הַמַּבְטִיחַ": "term used to indicate a direct object-the-promising",
 "נִסְקְלוּ": "we-will-clear it",
 "נִבְחֲנוּ": "we-will-they have tested",
 "וְהַסַּבְלָנוּת": "and-the-patience",
 "נִבְחַן": "to be tested",
 "כָּל־טִנּוּף": "every-dirtying",
 "הַמַּשְׁקִיף": "the-observer",
 "הִכְלַמְתֶּם": "disgrace-their",
 "לֹא־אֶצְמָא": "no-I-will-thirsty",
 "הֲלוֹם": "hither",
 "הַאֲמִינִי": "the-amino",
 "כְּרִיסְטוֹס": "Christ",
 "אַל־תַּעַמְלוּ": "Don't!-you/she-will-mischief-his",
 "אִם־בַּמַּאֲכָל": "if-in-the-food",
 "תִּרְחַץ": "you/she-will-wash",
 "וּמִן־הַמְסֻבִּים": "and-part-the-around",
 "פְּרַקְלִיט": "prosecutor",
 "וְהַפְּרַקְלִיט": "and-the-prosecutor",
 "יְאַשְּׁרוּנִי": "he-will-they will call happy-me",
 "עַל־עֶדְרָם": "super- (superhuman, supernatural)-arrange-them",
 "מָחְתָּל": "diapered",
 "תִּפְטַר": "you/she-will-emit",
 "תַּחְתֹּר": "you/she-will-to row",
 "וְהַמְיֻדָּעִים": "and-the-know(pl)",
 "בֶּן־חֶסְלִי": "a son of-eat off-my",
 "בֶּן־רֵישָׁא": "a son of-introduction",
 "בֶּן־אֶלְמְדָן": "a son of-I-will-from-Dan",
 "בֶּן־יוֹסֵי": "a son of-Yossi (Hebrew name)",
 "אַל־תִּתְבַּע": "Don't!-you/she-will-to demand",
 "אֶת־אֹהֲבֵיהֶם": "term used to indicate a direct object-to like-their",
 "לְתַשְׁלוּם": "to-payment",
 "וּמֻשְׁפָּעָה": "and-affected",
 "מוֹדֲדִים": "surveyor(pl)",
 "וְהִבְרִיק": "and-to shine",
 "אַל־תִּכְלָאוּ": "Don't!-you/she-will-imprisonment-his",
 "הֲתִרְצֶה": "to become reconciled (to someone else's desire)",
 "עַל־הַמַּחֲרֵשָׁה": "super- (superhuman, supernatural)-the-a pick-axe",
 "וְאֶת־מַלְקֹחוֹ": "and-hoe-tweezers-his",
 "תְּשׁוֹטֵט": "you/she-will-to wander around",
 "מַדְלִיק־נֵר": "wonderful-candle",
 "יְשִׂמֵהוּ": "he-will-he has made-it",
 "וְאֶת־הַפִּיגַם": "and-hoe-the-common rue (plant)",
 "מִשְּׂאוֹר": "from-leaven",
 "אֲסָמַי": "I-will-semi- (semiconductor, semitrailer)",
 "הִנָּפְשִׁי": "life-my",
 "וְאַל־תְּהַלְּכוּ": "and-nothing-you/she-will-went",
 "יִתְאַזֵּר": "he-will-you will gird",
 "אֶת־אֲרֻחָתָם": "term used to indicate a direct object-a caravan of-them",
 "לֹא־יְצַפֶּה": "no-he-will-to watch",
 "אֶת־הָעָב": "term used to indicate a direct object-the-thick",
 "פֶּן־יִסְחַב": "lest-he-will-to drag",
 "סְעוּדָה": "meal",
 "וְאֶת־אַחְיֹתָיו": "and-hoe-sister",
 "אֶת־הַהוֹצָאוֹת": "term used to indicate a direct object-the-bring out(pl)",
 "פֶּן־יְיַסֵּד": "lest-he-will-found",
 "יְתֻקָּן": "he-will-straighten",
 "וְלַחֲזוֹר": "and-to-the-courting",
 "הַמָּמוֹן": "the-money",
 "לְקָרֵר": "to-to cool",
 "יַכְשִׁיל": "he-will-axe",
 "הוֹסֵף": "to be added",
 "אֶל־הַשִּׁקְמָה": "at-the-sycamore",
 "וְהִשָּׁתְלִי": "and-to be transplanted-my",
 "אֲרוּחַת": "I-will-spirits",
 "יִבְרַק": "he-will-Berak",
 "לְהִתְרַפּוֹת": "to-relaxing",
 "וְהַנֹּאֲפִים": "and-the-adultery",
 "וְהַמּוֹכֵס": "and-the-customs official",
 "וְתוֹפֵף": "and-to drum",
 "וַאֲשֶׁר־בַּפְּרָזוֹת": "and-which-in-the-villages",
 "אֶת־פִּרְחָם": "term used to indicate a direct object-it has broken out-them",
 "וּבְדַאֲגוֹת": "and-in-be anxious(pl)",
 "תַּעַצְרוּ־כֹחַ": "you/she-will-they retained-strength",
 "מַדִּיחַ": "instigator",
 "זְהוֹרִית": "rayon",
 "נְבֻכוֹת": "we-will-Bacuth",
 "צָלוּי": "grilled",
 "וּבַתְּהִלִּים": "and-in-the-Psalms (book of the Bible)",
 "חֲתִירָה": "undermining",
 "לְהִתְיָעֵץ": "to-to consult (someone)",
 "בְּנֵי־רְגוֹשׂ": "the sons of-excitement",
 "וְאֶת־תַּדַּי": "and-hoe-you/she-will-was sufficiency",
 "וְאִם־נֶחְלְקָה": "and-whether?-to be divided",
 "יִתְקוֹמֵם": "he-will-you will raise up",
 "וְנֶחֱלָק": "and-to be divided",
 "יְגַדֵּפוּ": "he-will-they have blasphemed",
 "וְרָצוֹחַ": "and-murdered",
 "מִפֵּרוּרֵי": "from-suburban",
 "הִתְפַּתֵּחַ": "to develop",
 "וְכָל־הַמַּכְשִׁיל": "and-whole-the-hindering",
 "קִטֵּע": "section",
 "תְּתַקְּנוּ": "you/she-will-you will buy",
 "מִן־הַצְדּוּקִים": "from-the-Zadok(pl)",
 "קוּמָם": "to outrage",
 "הֲתִישַׁן": "to become old",
 "נִגְלְלָה": "to be rolled up",
 "אֶת־מִכְמְרוֹתָם": "term used to indicate a direct object-from-shrivel-them",
 "מַדְלִיקִים": "wonderful(pl)",
 "קָטוֹן": "reduction",
 "הִתְרַצֵּה": "to become reconciled (to someone else's desire)",
 "כִּי־הֲדוֹם": "that-foot-rest",
 "יִמְחַל": "he-will-am beginning",
 "לֹא־יִמְחַל": "no-he-will-am beginning",
 "וְאֶת־הַמָּמוֹן": "and-hoe-the-money",
 "הַטְּלַאי": "the-patch",
 "הַנֶּחֱלָקִים": "the-to be divided(pl)",
 "נֶחֱלָק": "to be divided",
 "תְּחֻיָּב": "insert (in magazine, newspaper etc.)",
 "תְּשֹׁטֵט": "you/she-will-a scourge",
 "יִנָּטֵל": "he-will-to take",
 "יְמַעֲכוּ": "he-will-they were handled",
 "וּנְלַקֵּט": "and-to be collected",
 "מִכָּל־הַזֵּרוֹעִים": "from-all-the-arm(pl)",
 "מִן־הַיְרָקוֹת": "from-the-vegetables",
 "לְתוֹכָהּ": "to-middleware",
 "אִם־מִלִּמוּד": "if-from-studying",
 "קֵיָסַרִיה": "Caesarea (city)",
 "וְנֶעְתַּק": "and-to be relocated",
 "גַּבָּאֵי": "manager of synagogue",
 "הַמַּכְשִׁיל": "the-hindering",
 "קִטֵּעַ": "section",
 "וּכְמוֹכֵס": "and-as-customs official",
 "הַמְסֹרָסִים": "the-castrated(pl)",
 "בְּהִתְחַדֵּשׁ": "in-to be renewed",
 "וְאֶת־מֹשְׁבוֹת": "and-hoe-seat(pl)",
 "וְהַמּוֹכְסִים": "and-the-tax-collectors",
 "כִּי־בֹלְעִים": "that-Bela(pl)",
 "גַּיֵּר": "to convert someone to Judaism",
 "הַיַּתּוּשׁ": "the-mosquito",
 "וְתוֹכָן": "and-astronomer",
 "וְגַרְגְּרָנוּת": "and-gluttony",
 "הַמְסֻיָּדִים": "the-whitewashed(pl)",
 "לַהֶגְמוֹן": "to-the-bishop",
 "אֶת־־הַהֵיכָל": "term used to indicate a direct object-is the-temple",
 "אִם־": "if",
 "עִם־הָעֲנָנִים": "with-the-clouds",
 "וְאֶת־עֲמָלְךָ": "and-hoe-to work-your",
 "יָעָפְתָּ": "jet lag",
 "יִנָּזֵק": "he-will-the injury of",
 "הַגָּנוּז": "the-hidden",
 "וְקַעֲרוֹת": "and-crater(pl)",
 "נִשְׁחַטְתָּ": "we-will-you will slaughter",
 "מַלְשִׁין": "informer",
 "הַמַּדִּיחַ": "the-instigator",
 "תְּכֻלְכַּל־שָׁם": "very pale blue-there",
 "וְאִם־עַוְלָתֵנוּ": "and-whether?-a sucking child of-our",
 "אֶת־הַמּוּלִים": "term used to indicate a direct object-the-in front of(pl)",
 "עַל־הָעָרְלָה": "super- (superhuman, supernatural)-the-foreskin",
 "גַּם־לַמּוּלִים": "also-to-the-in front of(pl)",
 "חִדּוּשׁ": "innovation",
 "הַחִמּוּד": "the-sweet",
 "כָּל־חִמּוּד": "every-sweet",
 "שֶׁנֶּחֱלַשׁ": "that-to weaken",
 "אִם־נִתְעַנֶּה": "if-we-will-you will afflict",
 "נְחַכֶּה": "we-will-adhere",
 "יַאֲשִׁימֵם": "he-will-I will make-them",
 "נִתְמַנּוּ": "we-will-will we complete",
 "כָּל־הַמִּתְקוֹמֵם": "every-the-insurrectionist",
 "מִן־הָרָשׁוּת": "from-the-authority (postal, port, lands)",
 "וְגָיוֹס": "and-enlistment",
 "אֶת־כָּל־הָעִסָּה": "term used to indicate a direct object-every-the-dough",
 "עוֹלְבִים": "insulting(pl)",
 "וְאַל־תַּחְקְרוּ": "and-nothing-you/she-will-explore",
 "תִּתְכַּסֶּה": "you/she-will-you will cover",
 "כָל־הָאֵבָרִים": "whole-the-mighty horses",
 "כָּל־הָאֵבָרִים": "every-the-mighty horses",
 "גַּם־בְּשִׂכְלִי": "also-in-mental",
 "הֶדְיוֹטוֹת": "layman(pl)",
 "לְהִתְקַבֵּל": "to-to be received",
 "בַּחֲסִידוּת": "in-the-Hassidism",
 "נִבְטַח": "we-will-rely",
 "תְּשַׁלְּחוּנִי": "you/she-will-send away-me",
 "בְּצִמְצוּם": "in-reduction",
 "נִתְגַּדֵּל": "we-will-may it be great",
 "וְעַל־הַפְּרִישׁוּת": "and-were from-the-asceticism",
 "הַמְּסוּרָה": "the-Massorah (notations regarding the exact",
 "תְּהִלִּים": "Psalms (book of the Bible)",
 "מִקֵּיסַרְיָה": "from-Caesarea (city)",
 "אֶל־דֶּרְבִּי": "at-derby",
 "הִתְוַכַּח": "to argue",
 "מִן־הַמִּקְרָאוֹת": "from-the-reading(pl)",
 "הַמַּדִּיחִים": "the-instigator(pl)",
 "כִּמְדֻמֶּה": "apparently",
 "אֶל־הַתֵּאַטְרוֹן": "at-the-theater",
 "הִצְטָרֵךְ": "to need",
 "אֶל־תּוֹכָהּ": "at-middleware",
 "אֶת־הָאֲנָךְ": "term used to indicate a direct object-the-vertical",
 "וְתִשְׁבָּחוֹת": "and-praises",
 "אֶל־הַמּוּלִים": "at-the-in front of(pl)",
 "הַקָּרְבָּנוֹת": "the-victimhood",
 "בְּסוּדָר": "in-sweater",
 "הַפְּרַקְלִיט": "the-prosecutor",
 "עַל־הַצְּלוּב": "super- (superhuman, supernatural)-the-crucified",
 "רַבּוּנִי": "sovereign",
 "מַטְלִית": "rag",
 "לִגְיוֹן": "legion",
 "אֶת־הָרְשׁוּת": "term used to indicate a direct object-the-permission",
 "וְהַמַּנְהִיג": "and-the-leader",
 "אֶת־הַבְּחִירִים": "term used to indicate a direct object-the-the chosen one of(pl)",
 "בִּשְׁעַת": "during",
 "נִקְצְרוּ": "we-will-they have reaped",
 "אֶת־נֵרוֹתֵיהֶן": "term used to indicate a direct object-lamps-their(f)",
 "הַקְּעָרוֹת": "the-crater(pl)",
 "נִצְדַּקְנוּ": "we-will-is righteousness-our",
 "לְאִסְפַּמְיָא": "to-Spain (only in idioms)",
 "בְּכַשְׂדִּית": "in-Chaldee",
 "כָּל־הַשְּׂכָלִים": "every-the-childlessness",
 "שֶׁהַלּוּחוֹת": "that-the-blackboard(pl)",
 "אַסְפְסוּף": "rabble",
 "וּלְהִבָּחֵן": "and-to-to be noticed",
 "וְחַמְדָנוּת": "and-greediness",
 "וְכָל־הָאֲבֵלִים": "and-whole-the-mourners",
 "אֶל־נַחֲלוֹתֵיהֶם": "at-to gain (victory)-their",
 "לוֹהֵט": "burning hot",
 "וְכָל־הַסּוֹבְלִים": "and-whole-the-suffering(pl)",
 "וְכוֹרְתִים": "and-beehive(pl)",
 "וּבְהִתְוַכְּחָם": "and-in-to argue-them",
 "אֶת־הַמְּשׂוּכָה": "term used to indicate a direct object-the-hedgerow",
 "לְהֵרָדֵם": "to-to be anesthetized",
 "בֵּינוֹנַי": "medium",
 "לְהִנָּהֵג": "to-to do something out of habit or custom",
 "לְהַפְצִיר": "to-to plead persistently",
 "וְהַשּׁוֹלְטִים": "and-the-dominant(pl)",
 "הַמּוּסָרִית": "the-ethically",
 "אֲדַמֵּם": "I-will-be dumb",
 "יַרְגִּיז": "he-will-irritable",
 "תִּכְלֹל": "to integrate",
 "נִתְמַנְּתָה": "we-will-Timnah-towards",
 "הָעֲלוּלוֹת": "the-liable(pl)",
 "וְלוּק": "and-look",
 "כְּדִלְקַמָּן": "as-following",
 "הֲדָחָה": "rinsing",
 "בְּהַנְהָגָתוֹ": "in-the-you led-his",
 "לְסַיְּעוֹ": "to-assistant-his",
 "וּבְהֵעָדְרוֹ": "and-in-is the-flock-his",
 "וּסִיּוּם": "and-end",
 "פִּסְקוֹ": "to cease-his",
 "בַּאֲדִישׁוּת": "in-the-apathy",
 "בְּפֵסֶק": "in-to cease",
 "שְׁמִיעָה": "hearing",
 "פְּרוֹטוֹקוֹלָהּ": "protocol-her",
 "פֵּרוּט": "details",
 "פֶּסֶק": "to cease",
 "רָגִיל": "regular",
 "פָּשׁוּט": "simple",
 "לְהִשָּׁאֵל": "to-Sheol",
 "זַכַּאי": "innocent",
 "וְהַהַצְהָרוֹת": "and-the-to be declared(pl)",
 "לְהַצְבִּיעַ": "to-to raise one's hand",
 "בְּמִלּוּי": "in-filling",
 "הִנַּחְתִּים": "is descending",
 "הַחֲזָרָתָם": "the-mumps-them",
 "אֲקַלֵּל": "I-will-curse",
 "הַחֲזָרַת": "the-mumps",
 "נִתְלָּא": "we-will-suspend",
 "מִן־הַסֵּדֶר": "from-the-order",
 "אַחְרָאִי": "responsible",
 "כְּאַפּוֹטְרוֹפּוֹס": "as-guardian",
 "מֵהַשֶּׁפַע": "from-to be influenced",
 "הַבֻּרְסְקִי": "the-tanner",
 "בְּחֲלִיפִין": "in-exchange",
 "שֶׁשַּׁיָּךְ": "that-to attribute",
 "עֲסָקֵיהֶם": "to deal with-their",
 "עֲסָקֵיכֶם": "to deal with-your(pl)",
 "לְהַדְפִּיס": "to-to type",
 "הַדְפָּסַת": "the-imprint",
 "וְכָל־הַכְּסָפִים": "and-whole-the-funds",
 "וְהַהַסְכָּמָה": "and-the-agreement",
 "הַסְּכוּם": "the-sum (of money)",
 "וּמוּכָח": "and-proven",
 "בְּהַסְכָּמָה": "in-the-schema",
 "אַפּוֹטְרוֹפְּסַי": "guardian-like",
 "וְלַנִּלְחָץ": "and-to-the-to be pressed",
 "לְמִבְחַן": "to-test",
 "בְּהַתְאָמָה": "in-matching",
 "הַצָּעוֹת": "to be advised(pl)",
 "מֵחֲזָרָה": "from-the way back",
 "נִסְפָּחוֹת": "appendix(pl)",
 "חֲלוּקוֹת": "division(pl)",
 "כָּל־הַמִּשְׂרוֹת": "every-the-from-the chief of(pl)",
 "נִסְפַּחַת": "we-will-flaking skin",
 "הַבִּישׁוֹפוּת": "the-diocese",
 "וְלִזְכּוֹת": "and-to one's credit",
 "חִיצוֹנִיּוֹת": "exterior(pl)",
 "וְכָל־הַחְלָטָה": "and-whole-decision",
 "לְהַחְלָטוֹתָיו": "to-the-to blanch-his",
 "מֵתִינוּת": "restraint",
 "וּבְסִדּוּר": "and-in-organizing",
 "בְּכָל־הַחְלָטוֹתֶיהָ": "among-all-the-to blanch-her",
 "לְהַטָּפָה": "to-the-drop (liquid)",
 "וְנִהוּל": "and-management",
 "וְשַׁיָּךְ": "and-to attribute",
 "בְּיֻחָסִין": "in-family tree",
 "הִשַּׂמְתִּיךָ": "I will make-you",
 "לְהֻפְרָשׁ": "to-difference",
 "בְּסִיּוּעַ": "in-aid",
 "בְּכָל־סָנִיף": "among-all-branch",
 "וְהַמִּקְרִים": "and-the-source(pl)",
 "הַבִּישׁוֹף": "the-bishop",
 "לְהַחְלִיט": "to-to decide",
 "הַהַחְלָטָה": "the-decision",
 "וְהַחְלָטָה": "and-the-to blanch",
 "סוֹפִית": "finally",
 "בִישׁוֹף": "bishop",
 "נִפְרֶדֶת": "we-will-the mule of",
 "מִנְּשִׂיאוּת": "from-presidency",
 "אַחְרָיוּת": "responsibility",
 "כָּל־הָאֻמּוֹת": "every-the-tribes",
 "וְאַחְרָאִיּוֹת": "and-responsible person(pl)",
 "רִאשׁוֹנֵי": "initial",
 "הַבִּימָה": "the-stage (noun)",
 "וְהַהַלְבָּשָׁה": "and-the-clothing",
 "לִכְבוֹדְךָ": "to (before the address in a letter or on an envelo-your",
 "יִתְקַדֵּשׁ": "he-will-it should be set apart",
 "נוֹכְחוּתְךָ": "attendance-your",
 "הָעוֹבְדִים": "the-worker(pl)",
 "קְדוֹשׁוֹת": "the holy one of(pl)",
 "הַמְכַבְּדִים": "the-honorable(pl)",
 "לְבַלְבֵּל": "to-in-the-not to",
 "וּלְהַדְהִים": "and-to-to astound",
 "וְלַדִּבּוֹת": "and-to-the-a bear(pl)",
 "וְגַמוּרָה": "and-finished",
 "יִתְקַיֵּם": "he-will-you will set up",
 "הַשָּׁבוּעוֹת": "the-Shavuot",
 "מְפֻצָּלוֹת": "split(pl)",
 "סוֹעָה": "gale",
 "אַדִּירָה": "majestic",
 "וּבְהַכְרִיזָם": "and-in-to announce-them",
 "יַחְתְּמוּ": "he-will-they seal up",
 "יְתֵדוֹתֶיהָ": "stake-her",
 "הָעִקֵּשׁ": "the-perverse",
 "חֲבֵרֵינוּ": "to join (people)-our",
 "הָעוֹזֵר": "the-assistant",
 "נוֹרָאִים": "terrible(pl)",
 "נִמְלָאִים": "to be filled(pl)",
 "דְּהַיְנוּ": "that is",
 "הַנֶּאֱדָרִים": "the-glorious(pl)",
 "הַמְזוּהִים": "the-pantry(pl)",
 "בַּאֲמִתּוּת": "in-the-veracity",
 "וְסוֹבְלֵיהֶם": "and-suffering-their",
 "וַעֲנָוֶיהָ": "and-they abused-her",
 "הַמְּרֻסָּסִים": "the-atomizer(pl)",
 "אַדְּרוֹת": "be great(pl)",
 "וְנִקְצֹר": "and-to be reaped (grain)",
 "נְעָרֵב": "we-will-pleasant",
 "הַזּוֹהֲרִים": "the-shining(pl)",
 "הַמְּאִירִים": "the-Meir (Hebrew name)(pl)",
 "בְּפַרְסֵם": "in-to be publicized",
 "תַּעֲדִיף": "you/she-will-preferable",
 "אֲמַשֵּׁשׁ": "I-will-feel of",
 "צְלַבְכֶם": "cross-your(pl)",
 "תְּרוֹמְמוּ": "you/she-will-exalt",
 "וּמֻרְשִׁים": "and-impressive",
 "הוּטַל": "to be imposed",
 "אַל־יִתְחַיֵּב": "Don't!-he-will-insert (in magazine, newspaper etc.)",
 "אֶת־עִסְקֵיהֶם": "term used to indicate a direct object-to deal with-their",
 "אֶת־הַטִּפָּה": "term used to indicate a direct object-the-drop (liquid)",
 "וּבָאָבִיב": "and-in-the-spring (season)",
 "וּלְחוֹבוֹת": "and-to-debt(pl)",
 "תִּתְבָּרֵךְ": "you/she-will-you bless",
 "וּכְקְרִיאוֹת": "and-as-legibility",
 "לַמַּדְפִּיס": "to-the-printer (person)",
 "וְהִפָּטֵר": "and-to be absolved",
 "וּלְאוֹלִיבֵר": "and-to-Oliver",
 "הִצְטַדְּקוּת": "self-justification",
 "בְּכָל־הַחוֹבוֹת": "among-all-the-debt(pl)",
 "קְשִׁיחוּת": "stubbornness",
 "הַצְּרִיכָה": "the-consumption",
 "אֶת־חוֹבוֹת": "term used to indicate a direct object-debt(pl)",
 "וְהַמְפַקְּחִים": "and-the-supervisor(pl)",
 "וּמְפַקֵּחַ": "and-supervisor",
 "הִתְקַבְּלָם": "to be received-them",
 "בְּהִתְנַהֲגוּת": "in-behavior",
 "הִגִּישׁ": "to serve (food, drink)",
 "חִלּוּק": "division",
 "הַנִּתְפָּס": "the-to be caught",
 "הַמְּהַוּוֹת": "the-what is?(pl)",
 "רְשִׁימָה": "list",
 "מְסֻדֶּרֶת": "typesetting machine",
 "תִּנָּקֵב": "you/she-will-to stipulate",
 "תִּנְקֹב": "you/she-will-to stipulate",
 "תִּנָּטֶה": "you/she-will-to be inclined (to do something)",
 "תִּגְבַּר": "to reinforce",
 "לְהַסְבִּיל": "to-the-passive",
 "נִתְלָה": "to hang from",
 "גּוֹלְלִים": "to wind(pl)",
 "סַמְכוּתוֹ": "authority-his",
 "בְּשִׁכְנוּעַ": "in-convincing",
 "צְבִיעוּת": "hypocrisy",
 "בְּחָרִיפוּת": "in-sharpness",
 "אֶל־הַמּוּכָח": "at-the-proven",
 "תְּעַטֵּר": "you/she-will-encircle",
 "תִּזְעַם": "you/she-will-to be furious",
 "תִּסָּחֵב": "you/she-will-to drag",
 "יִפְעַר": "he-will-open",
 "וּסְכוּם": "and-sum (of money)",
 "וּבָאֶנְצִיקְלוֹפֶּדְיוֹת": "and-in-the-encyclopedic(pl)",
 "וּלְהַגִּישׁ": "and-to-to serve (food, drink)",
 "וְהַנְּלוֹזוֹת": "and-the-corruptedness",
 "בְּכָל־צִבְעָם": "among-all-color-them",
 "תִּקְרָאֵהוּ": "you/she-will-call on-him",
 "נִכְרְעוּ": "we-will-they bowed down",
 "וְעָרִיצוּת": "and-tyranny",
 "בְּהִנָּהֲגָהּ": "in-leadership",
 "הַמְּלֻטֶּשֶׁת": "the-polishing machine",
 "אֶשָּׂאֵהוּ": "I-will-carry-it",
 "הַנּוֹסֵעַ": "the-traveler",
 "לְטִבְלוֹתֵיכֶם": "to-to immerse-your(pl)",
 "וְעַצְּרוֹתֵיכֶם": "and-inclose-your(pl)",
 "נִסְדָּרִים": "we-will-order",
 "הַמְעַכְּבִים": "the-delayed(pl)",
 "אֶת־קָרְבְּנוֹת": "term used to indicate a direct object-victimhood",
 "לַנּוֹסֵעַ": "to-the-traveler",
 "סְכוּם": "sum (of money)",
 "כָּל־מְנָיָה": "every-stock",
 "אַלְמוֹן": "Rangoon creeper",
 "בַּבִּיט": "in-the-bit",
 "נִקְבְּעָה": "to be decided",
 "הָאָרְסִי": "the-poisonous",
 "וּבְהוֹשַׁעְנָא": "and-in-a willow branch beaten on the grou",
 "הַהֶסְכֵּם": "the-agreement",
 "הַשַּׁיָּכוֹת": "the-relevance",
 "וּלְרֵאשׁוּת": "and-to-chairmanship",
 "לְכָל־הַפְּקוּדוֹת": "to-whole-the-mandate(pl)",
 "אֲיַעֵד": "I-will-to designate",
 "וּבְכָל־הַיְּתֵדוֹת": "and-in-whole-the-stake(pl)",
 "אֶת־עֲמָלְךָ": "term used to indicate a direct object-to work-your",
 "וְלַסֵּדֶר": "and-to-the-order",
 "אֶסְגֹּר": "I-will-to close",
 "לְהַקְבִּיל": "to-the-acceptable",
 "וְהָאֲסִירָה": "and-the-I will remove",
 "וּבְמוּבָן": "and-in-clear",
 "וּבְיִחוּד": "and-in-uniqueness",
 "תִּפְצַח": "you/she-will-break",
 "הוֹשֵׁט": "to be floated",
 "יִלְחַץ": "he-will-to press",
 "יִלְחָץ": "he-will-to press",
 "נִרְאֶנּוּ": "we-will-is seeing-us",
 "הַכַּוָּנָה": "the-intention",
 "וְאִלּוּלֵי": "and-if ... not",
 "נְשׁוֹתֵיהֶם": "man-their",
 "וּתְנָאֶיהָ": "and-teacher-her",
 "שֶׁנּוֹסַד": "that-to be founded",
 "יְזֻעְזַע": "he-will-to be shaken",
 "וּלְנִשּׂוּאֵיהֶם": "and-to-certainly-their",
 "הִתְנַשְּׂאוּת": "arrogance",
 "מִתְקַבֶּלֶת": "from-parallelism",
 "הַמּוֹבִיל": "the-shipper",
 "הַהִתְנַשְּׂאוּת": "the-arrogance",
 "הִתְנַשְּׂאוּתְכֶם": "arrogance-your(pl)",
 "כְּמִנּוּיִי": "as-appointing-my",
 "נְשׁוֹת": "man(pl)",
 "מֵהִתְנַשְּׂאוּתוֹ": "from-arrogance-his",
 "הִתְנַשְּׂאוּתְךָ": "arrogance-your",
 "שַׁיָּכוֹת": "relevance",
 "יִרְחַב": "he-will-roomy",
 "תִּסָּלֵל": "you/she-will-to pave",
 "וּבַחַלָּשׁוֹת": "and-in-the-weakness",
 "קִבְּלָנִי": "contractual",
 "וּלְהַעֲנִישׁ": "and-to-to punish",
 "וְהָפָרַת": "and-the-is the Euphrates",
 "תְּדֻכֶּה": "you/she-will-collapse",
 "הִתְנַהֲגוּת": "behavior",
 "גוּפָנִית": "physically",
 "לְהִתְעַסֵּק": "to-to occupy oneself",
 "לְהַשְׁפִּיעַ": "to-to influence",
 "חָמוּס": "European polecat",
 "הִתְכּוֹנֵן": "to prepare oneself",
 "וְקִפֵּל": "and-to fold",
 "לְהִדָּחוֹת": "to-trip up",
 "יִתְאַסֵּף": "he-will-she will be received",
 "וּבְקִיאִים": "and-in-vomitus(pl)",
 "חֲרִישָׁה": "plowing",
 "תְּחַפֵּשׂ": "to dress someone in a costume",
 "לְפַרְנָס": "to-to support",
 "וּפַרְנָסוֹ": "and-to support-his",
 "נוּגֶה": "sad",
 "פֻּרְעָנוּתָם": "calamity-them",
 "הַלּוֹהֵט": "the-burning hot",
 "הֻרְשׁוּ": "take possession of",
 "הָאַחֲרָיוּת": "the-responsibility",
 "לְעִקְּרֵי": "to-main",
 "וּבְגָלַטְיָא": "and-in-Galatia",
 "אָרְגַּן": "to be organized",
 "נִפְעֲלָה": "Niph'al",
 "בְּשָׁהוּתוֹ": "in-time-his",
 "לְהִתְכַּסּוֹת": "to-you cover(pl)",
 "מְרַמֵּז": "hinted",
 "הִפָּרְדוּת": "separation",
 "סְמִיכוּתִי": "proximity-my",
 "וּסְמִיכוּת": "and-proximity",
 "יִיעַץ": "he-will-to advise",
 "וְהַפְּשׁוּטִים": "and-the-simple(pl)",
 "אֶתְנַצֵּל": "I-will-will you be delivered?",
 "הַמּוּפָר": "the-breached",
 "הִתְנַהֵג": "to behave",
 "הִתְמַסֵּר": "to devote oneself",
 "תְּפַקְפֵּק": "you/she-will-to hesitate",
 "הַנִּגְנָזִים": "the-to be hidden(pl)",
 "הִמְשַׁכְתָּ": "you will march",
 "וְהוֹסֵף": "and-to be added",
 "תַּעֲמֹל": "you/she-will-to work",
 "הִתְחַפַּשְׂתָּ": "costume",
 "תְּתַרְגֵּם": "you/she-will-translate",
 "אֲבַלְבֵּל": "I-will-to confuse",
 "יִבְנוּהוּ": "he-will-they rebuilt-it",
 "יִסְפֹּד": "he-will-mourn",
 "אֶת־כָּל־הָעֲמֵלִים": "term used to indicate a direct object-every-the-workmen",
 "אֶת־צְלָבְךָ": "term used to indicate a direct object-cross-your",
 "כָּל־עֲבוֹדָתְךָ": "every-the service of-your",
 "תְּצַוּוּ": "you/she-will-command",
 "וּלְמִנְעָלִים": "and-to-footwear(pl)",
 "הַצְּנִיעוּת": "the-modesty",
 "הַמֵּכִיל": "to load into a container",
 "אֶפְרוֹחֶיהָ": "chick-her",
 "הָרוּחָנִית": "the-spiritually",
 "נִפְתֵּיתָ": "we-will-will you deceive",
 "וּלְהַצָּלָתְךָ": "and-to-you have delivered-your",
 "בֶּרוֹז": "duck (noun)",
 "הַמַּלְבִּין": "the-whitening",
 "רוֹפֵא": "doctor",
 "נְכָלֵי": "we-will-things-my",
 "תַּחְשֹׂכוּ": "you/she-will-they have withheld",
 "תִגְבַּר": "to reinforce",
 "מוּטָבִים": "it is preferable(pl)",
 "נִשְׁלַחְתָּ": "we-will-you sent",
 "הִטְבַּלְתָּ": "you will dip",
 "וּבַמַּפְתְּחוֹת": "and-in-the-the key of(pl)",
 "וְאֶת־הָעֲשִׁירִים": "and-hoe-the-rich people",
 "לְהִמָּכֵר": "to-to sell",
 "וְהִפְרִישׁ": "and-to secrete",
 "עֵדוּיוֹת": "adorned(pl)",
 "יִתְקַיָּם": "he-will-you will set up",
 "פְּשׁוּטִים": "simple(pl)",
 "הֵיכָן": "where?",
 "לְבַסֵּס": "to-in-the-horse",
 "אֶגְעַר": "I-will-chide",
 "זוּגוֹ": "pair-his",
 "וּזְהִירִים": "and-careful(pl)",
 "תִּמְסֹר": "you/she-will-to give",
 "גְּנַאי": "shame",
 "פְּרָטֵי": "private",
 "לְהִלָּמֵד": "to-to learn",
 "תַּחֲשֹׂכוּ": "you/she-will-they have withheld",
 "הַטּוֹעֵן": "the-pleader",
 "הֻפְרְשׁוּ": "offal-its",
 "כְּשִׁעְבּוּד": "as-slavery",
 "הִתְקַיֵּם": "to take place",
 "וּפֻרְעָנוּת": "and-calamity",
 "הַפֻּמְבִּיּוֹת": "the-publicity",
 "הַהַשְׁרָאָה": "the-inspiration",
 "מִגְוַן": "from-to vary",
 "יְהֵא": "will be",
 "טוֹעֵן": "pleader",
 "סְדוּרִים": "organizing(pl)",
 "אֲבָרְכֶנּוּ": "I-will-we bless",
 "וְהָאוֹסֵר": "and-the-I was disciplined",
 "הַמְבַזְבֵּז": "the-wasted",
 "לְהִזְדַּעֲזֵעַ": "to-to be shocked",
 "וּלְהִתְרוֹמֵם": "and-to-to rise up",
 "וּלְהִשָּׁפֵל": "and-to-to be humiliated",
 "וְהַסּוֹבְלִים": "and-the-suffering(pl)",
 "וְלַצְּבוּעִים": "and-to-the-painted(pl)",
 "אֶתְוַכַּח": "I-will-you reprove",
 "יִתְנַהֵג": "he-will-you have led away",
 "הָעוֹדֵף": "the-leftover",
 "בְּמִיזוּרִי": "in-Missouri",
 "וְהַנִּצְרָךְ": "and-the-to be consumed",
 "הַמְלָצָה": "recommendation",
 "תִּנָּטַע": "you/she-will-to plant (a tree)",
 "חַמְדָנוּת": "greediness",
 "הַמֶּרְכָּזִי": "the-central",
 "יִנָּטַע": "he-will-to plant (a tree)",
 "לְמַדְפִּיס": "to-printer (person)",
 "וּלְהַגִּיהַּ": "and-to-to proofread",
 "וְהַסּוֹכֵן": "and-the-agent",
 "בַּשְּׁלִיחוּת": "in-the-mission",
 "תִּנָּתֶנָּה": "you/she-will-she gave",
 "לְהִתְעַלּוֹת": "to-she came up(pl)",
 "וְלַגְּבוֹהִים": "and-to-the-elevated(pl)",
 "תֵּאוּר": "description",
 "לַסּוֹכֵן": "to-the-agent",
 "הַנִּגְלִים": "the-to be rolled(pl)",
 "וְהַמְּטַפֵּס": "and-the-climber (plant)",
 "וּלְשִׁמּוּשׁוֹ": "and-to-use-his",
 "לְהַפְרָזָה": "to-the-bombast",
 "תִּנֹּעַ": "momentum",
 "הִרְשֵׁיתִי": "to net (a ball)-my",
 "לְהִבָּשֵׁל": "to-boiled",
 "סָנֵגוֹרְכֶם": "defense attorney-your(pl)",
 "שְׁלִיחוּתְכֶם": "mission-your(pl)",
 "רְשׁוּמָה": "record",
 "תִּתְקַיֵּם": "you/she-will-you will set up",
 "נוֹבֵעַ": "gushing",
 "הָאַחֲרַאי": "the-responsible person",
 "לְסוֹכֵן": "to-agent",
 "הִכְאִיב": "to hurt",
 "לְהִתְלוֹצֵץ": "to-to joke",
 "לְעִסְקוֹ": "to-to deal with-his",
 "וּלְשְׁלִיחוּתוֹ": "and-to-mission-his",
 "עֵסֶק": "business",
 "עָטוּי": "wrapped",
 "וְהִתְוַכֵּחַ": "and-to argue",
 "לְהִטָּרֵד": "to-to expel",
 "הֻצְּעָה": "to be advised",
 "תִּפְשְׁטוּ": "you/she-will-they made a raid",
 "הַגּוּפָנִית": "the-physically",
 "הַטִּבְעִית": "the-predictably",
 "הוֹוֶה": "present time",
 "וְהֻסְמַךְ": "and-to be authorized",
 "וּלְהִסָּמֵךְ": "and-to-to be authorized",
 "מֻרְשִׁים": "impressive",
 "וְהַכְּסָפִים": "and-the-funds",
 "וְסִיּוּעַ": "and-aid",
 "יִנְסַע": "he-will-to ride",
 "בּוֹרֵר": "arbitrator",
 "וּכְפוֹעֵל": "and-as-worker",
 "וּבְהַזְהָרָה": "and-in-warning",
 "יִתְחַבֵּר": "he-will-to arrange words in a certain syntactic relationsh",
 "וּמְעֻטָּרִים": "and-adorned(pl)",
 "הַמְחֻיָּב": "the-obligated",
 "יְפַרְנֵס": "he-will-to support",
 "תֵיֶר": "to be toured",
 "נִשְׁחַט": "to be slaughtered",
 "מִתְגַּבְּרִים": "from-to reinforce(pl)",
 "מִנּוֹכְחוּת": "from-attendance",
 "יְסַיֵּם": "he-will-to finish",
 "וּמֵאַפּוֹלּוֹס": "and-from-Apollos",
 "יְעֻטַּר": "he-will-encircle",
 "וְהַשּׁוֹבְרָהּ": "and-the-coupon-her",
 "וְהַדֻּגְמָה": "and-the-example",
 "הַסְּמִיכָה": "the-ordination",
 "מִמָּמוֹן": "from-money",
 "בְּטַקְסֶיהָ": "in-ceremony-her",
 "טַקְסֶיהָ": "ceremony-her",
 "לְחִדּוּשׁ": "to-innovation",
 "זְהִירָה": "radiance",
 "וְהַגְּנַאי": "and-the-shame",
 "הַגְּנַאי": "the-shame",
 "וְאֶרֶס": "and-poison",
 "נוֹסֵעַ": "traveler",
 "יַאֲכִיל": "he-will-edible",
 "אָלְבֶּנִי": "Albanian (person)",
 "בּוֹסְטוֹן": "Boston",
 "וְהַחֻרְבָּן": "and-the-destruction",
 "וּמְחַדֵּר": "and-intrusion",
 "תְּאַסְפוּ": "you/she-will-they have gathered",
 "וְשׁוּשֶׁלֶתְכֶם": "and-dynasty-your(pl)",
 "בְּרִיטַנְיָה": "Britain",
 "וְלוֹהֵט": "and-burning hot",
 "תִּכָּתֵר": "you/she-will-enclose",
 "שׁוֹבֵר": "coupon",
 "מַסְלוּלֵי": "of or relating to a path",
 "בְּהִתְגַּלְגְּלָם": "in-to roll-them",
 "בְּשָׁעָתוֹ": "during-his",
 "בָּאַזְהָרָה": "in-the-warning",
 "אֲמַהֵר": "I-will-quickly",
 "בְּתֵאוֹרְיָה": "in-theory",
 "יִמְצָאֵנִי": "he-will-they found-me",
 "וּוַדַּאי": "and-certainty",
 "הָעָף": "the-to fly",
 "צְחוֹקְכֶם": "laughter-your(pl)",
 "לְהִתְעַצֵּל": "to-to be lazy",
 "הִתְלַבְּשׁוּ": "you clothe yourselves",
 "לְרֵאשׁוּת": "to-chairmanship",
 "לְהַדְרָכָתָם": "to-the-you trod-them",
 "בַּהַחְלָטָה": "in-the-decision",
 "מַבָּע": "expression",
 "יַתְחִיל": "he-will-she is in labor",
 "הַדֻּגְמָה": "the-example",
 "קוֹשְׁרִים": "rebel(pl)",
 "הַטַבָּק": "the-tobacco",
 "וְשִׁמּוּשׁ": "and-use",
 "וְהַשִּׁפּוֹן": "and-the-concealed",
 "וְהַשְּׂעוֹרָה": "and-the-barley",
 "גְנַאי": "shame",
 "וּשְׁלִיחוּתְכֶם": "and-mission-your(pl)",
 "הוֹסָפוֹת": "addition",
 "לְהִשְׁתַּחֲווֹת": "to-prostration",
 "בַּתְּחוּם": "in-the-area",
 "מוּכָח": "proven",
 "הִיסְטוֹרְיָה": "history",
 "תִּכְנוּן": "planning",
 "וְהָכָנַת": "and-the-colleague",
 "לַנְּשִׂיאוּת": "to-the-presidency",
 "מוּכָחִים": "proven(pl)",
 "וְשֻׁתָּף": "and-to include",
 "יְסַיֵּעַ": "he-will-assistant",
 "וְהָרָזִים": "and-the-secret(pl)",
 "נִדְכֵּית": "we-will-which you have crushed",
 "בְּכָל־מִשְׂרוֹתֵיהֶם": "among-all-from-the commander of-their",
 "תְּטַרֵד": "you/she-will-to expel",
 "וְחַמְדָנוּתָם": "and-greediness-them",
 "בְּסַכָּנָה": "in-danger",
 "דֻּגְמָה": "example",
 "הַמִּזְרָחִית": "the-east of",
 "אֲסַמֵּךְ": "I-will-to depend on",
 "נִיסְּרָה": "we-will-discipline",
 "גּוּלְד": "(slang) Woe! Help!",
 "סִימָן": "symbol",
 "לְהַפְלִיל": "to-the-magistrate",
 "לְסִיּוּם": "to-end",
 "לָעִתּוֹנוּת": "to-the-press",
 "פֻּמְבִּיּוֹת": "public(pl)",
 "הַחֲגִיגִי": "the-festive",
 "וּמַכְחִישׁ": "and-denier",
 "הַטֶּקֶס": "the-ceremony",
 "הָאֵרוּעַ": "the-event",
 "הַקּוֹנְגְּרֶס": "the-congress",
 "הֵצִיעַ": "to advise",
 "הַחֲתִימָה": "the-signature",
 "כְּמֻסְמָךְ": "as-authorized",
 "קִטְעִים": "section(pl)",
 "נְאֻמוֹת": "we-will-I should die",
 "הִתְנַגְּדוּת": "objection",
 "חִלּוּט": "forfeiture",
 "וּבִטּוּל": "and-cancellation",
 "וְחִלּוּט": "and-forfeiture",
 "וּבְכָךְ": "and-in-like this",
 "וְלַעֲסֹק": "and-to-the-to deal with",
 "נִפְסָקִים": "to stop(pl)",
 "שֻׁחְרַר": "to be released",
 "אַפְּרִיל": "April",
 "הֻגַּשׁ": "to be served",
 "בָּרֵאשׁוּת": "in-the-chairmanship",
 "הִתְבּוֹנְנוּת": "observing",
 "הִתְרַחֲבוּת": "expanding",
 "וּבְרְצִינוּת": "and-in-seriousness",
 "סַמְכוּתָהּ": "authority-her",
 "תִּשְׁאוּל": "preliminary inquiry",
 "לְוַדֵּא": "to-to confirm",
 "בִּרְצִינוּת": "seriously",
 "מֶרְיוֹן": "jird (rodent)",
 "רוֹמְנִי": "Romanian person",
 "הַהַצְבָּעָה": "the-voting",
 "אִם־תִּכּוֹנֲנוּ": "if-you/she-will-they have established",
 "אֲאַבֵּד": "I-will-certainly",
 "אִם־בַּסָּכָל": "if-in-the-a fool",
 "עַל־מַה־שֶּׁכָּתוּב": "super- (superhuman, supernatural)-what?-revision",
 "נִמְלֹךְ": "to consult (someone)",
 "הִצִּיג": "to perform",
 "מִתְגָּאִים": "from-crown(pl)",
 "אֶת־הַשְּׂאוֹר": "term used to indicate a direct object-the-leaven",
 "עִסָּה": "dough",
 "יְרִידָה": "descent",
 "מִן־הָעֲלוּבִים": "from-the-forlorn(pl)",
 "וּמִן־הָעֲשׁוּקִים": "and-part-the-oppression",
 "אַל־תַּשִּׂיאוּ": "Don't!-you/she-will-loftiness-his",
 "שְׁלִיחוּתִי": "mission-my",
 "שֶׁנִּקְצֹר": "that-to be reaped (grain)",
 "כָּרְשׁוּת": "as-all-permission",
 "אִם־אֲבַשֵּׂר": "if-I-will-bear the news",
 "אֲבַשֵּׂר": "I-will-bear the news",
 "הַנִּתְּנָה־־לִּי": "the-she gave-to-me",
 "בָּאִצְטַדְיוֹן": "in-the-stadium",
 "לְהִתְגּוֹשֵׁשׁ": "to-to struggle with",
 "אִם־אֲדַכֵּא": "if-I-will-crush",
 "וְלֹא־נְנַסֶּה": "and-no-we-will-it has fled",
 "תִּדּוֹן": "you/she-will-Don (title)",
 "אֶת־הַקַּבָּלוֹת": "term used to indicate a direct object-the-to complain (about something)(pl)",
 "מְנַוֵּל": "evil",
 "תִּתְגַּלָּח": "you/she-will-she shaved off",
 "אֲשַׁבֵּחַ": "I-will-I congratulated",
 "הַנִּבְצָע": "the-to be sliced",
 "אִם־נִבְחַן": "if-to be tested",
 "נִוָּסֵר": "we-will-and-he will turn aside",
 "נְחֻיַּב": "we-will-owe",
 "פֶּן־תִּוָּעֲדוּ": "lest-you/she-will-and-Iddo",
 "אֲתַקֵּן": "I-will-straighten",
 "אֶת־הָאֵבָרִים": "term used to indicate a direct object-the-mighty horses",
 "לַגָּרוּעַ": "to-the-bad",
 "אֶת־כָּל־הוֹנִי": "term used to indicate a direct object-every-Hun",
 "תִּבָּטֵל": "you/she-will-desist from labor",
 "וּמַה־יְּנֻגָּן": "and-what?-he-will-beat",
 "הַהֶדְיוֹטוֹת": "the-state of being a layman",
 "תִינוֹקוֹת": "baby(pl)",
 "הֶדְיוֹט": "layman",
 "וְאִם־חֶפְצָן": "and-whether?-objectify",
 "וְאַל־תִּכְלְאוּ": "and-nothing-you/she-will-imprisonment-his",
 "גִּבּוּי": "backup",
 "אֲחַכֶּה־לּוֹ": "I-will-adhere-for-him",
 "מָרַן": "our master",
 "הִבַּטְנוּ": "belly-his",
 "וְאִם־נִתְוַדֶּה": "and-whether?-we-will-thanks",
 "וְכָל־הָאֹהֵב": "and-whole-the-were loving",
 "וּבָאֲמִתִּי": "and-in-the-maidservant-my",
 "חָזַר": "to return",
 "תִּגְדְּלוּ־בוֹ": "you/she-will-greatness-his-is in-it",
 "וְלֹא־כְאִלּוּ": "and-no-like these",
 "אֶגְרוֹף": "fist",
 "נִמְצֵאנוּ": "we-will-we have found",
 "וּבְחַבְּבֵנוּ": "and-in-to love-our",
 "וְאֶת־תְּלָאָתֵנוּ": "and-hoe-suspend-our",
 "עֲצָרָנוּ": "inclose-our",
 "בְּאַתּוּנָה": "in-Athens",
 "יְגִיעָתֵנוּ": "hard work-our",
 "ְמְפֻכָּחִים": "realistic(pl)",
 "לֹא־יְעָדָנוּ": "no-to designate-our",
 "וְאִם־נִישָׁן": "and-whether?-we-will-sleeping",
 "אֶת־הָעֲמֵלִים": "term used to indicate a direct object-the-workmen",
 "תְּכַבּוּ": "you/she-will-they were quenched",
 "לֹא־צְבוּעָה": "no-painted",
 "אֳנִיַּת": "lobule",
 "הִתְרַחֵק": "to move away from",
 "פְּסוּלוֹת": "invalid(pl)",
 "תִּרְגּוּל": "exercise",
 "אַל־תִּגְעַר": "Don't!-you/she-will-chide",
 "וְאֶת־הַצְּעִירוֹת": "and-hoe-the-youth",
 "וְהִכְנִיסָה": "and-to insert",
 "אֶת־הָעֲשׁוּקִים": "term used to indicate a direct object-the-oppression",
 "לְשׁוֹטֵט": "to-to wander around",
 "לְהַסְפִּיק": "to-to be sufficient",
 "וְאִם־נִלְחָצִים": "and-whether?-we-will-are oppressing",
 "נִלָחֵץ": "to be pressed",
 "נְנֻחַם": "we-will-to be consoled",
 "מִן־הַמִּיתָה": "from-the-death",
 "אִם־עֹזְרִים": "if-to help(pl)",
 "וְאִם־הֶעֱצִיב": "and-whether?-to sadden",
 "סְחוֹרָה": "merchandise",
 "לֹא־שֶׁכְּשֵׁרִים": "no-that-be acceptable(pl)",
 "לְהִבָּטֵל": "to-desist from labor",
 "לְעַקֵּם": "to-crooked",
 "נִלְחָצִים": "we-will-are oppressing",
 "נִרְדָּפִים": "we-will-pursuers",
 "יִתְחַדֵּשׁ": "he-will-you may renew",
 "הַסְכָּמָה": "the-schema",
 "רַק־נִלְחַצְנוּ": "only-we-will-oppression-our",
 "וְאֶת־אֶבְלְכֶם": "and-hoe-to mourn-your(pl)",
 "הָעֹלֵב": "the-to insult",
 "עֲנִיּוּתָם": "poverty-them",
 "וּבְכָל־זְרִיזוּת": "and-in-whole-nimbleness",
 "וּמְחַוֶּה": "and-tribute",
 "הַגָּבוּי": "the-backup",
 "הַגְּבוּיָה": "the-backup",
 "כִּי־מַשְׁגִּיחִים": "that-is gazing(pl)",
 "לְהַַשְׁפִּיעַ": "to-to influence",
 "סִפּוּקְכֶם": "satisfaction-your(pl)",
 "לְכָל־הַתְּמִימוּת": "to-whole-the-honesty",
 "נִכְסָפִים": "we-will-funds",
 "עַל־מַתְּנָתוֹ": "super- (superhuman, supernatural)-gifts-his",
 "יַחֲזֹר": "he-will-to return",
 "חָלוּשׁ": "weak",
 "גַּם־עָדֵיכֶם": "also-eternity-your(pl)",
 "תִּשָּׂאוּנִי": "you/she-will-bear with-me",
 "מִן־הַתְּמִימוּת": "from-the-honesty",
 "יְשַׁעְבֵּד": "he-will-to enslave",
 "יִרְהַב": "he-will-importune",
 "אֶרְהַב": "I-will-importune",
 "שֶׁל־לִיסְטִים": "on account of-(carpentry) (colloquial) molding(pl)",
 "אֶחֱלָשׁ": "I-will-to control",
 "אֶתְרוֹמֵם": "I-will-it exalts",
 "אֶתְרוֹמָם": "I-will-it exalts",
 "תִּשְׁרֶה": "you/she-will-is Sarah",
 "אֲפַזֵּר": "I-will-scatter",
 "אֲפֻזַּר": "I-will-scatter",
 "וּרְכִילוּת": "and-gossip",
 "הִבָּחֲנוּ": "they have tested",
 "תִּכּוֹנָנוּ": "you/she-will-they are established",
 "וְלַחֲסִידוּת": "and-to-the-Hassidism",
 "אֶת־הַפְּרִישׁוּת": "term used to indicate a direct object-the-asceticism",
 "אֶת־הַסַּבְלָנוּת": "term used to indicate a direct object-the-patience",
 "וְעַל־הַסַּבְלָנוּת": "and-were from-the-patience",
 "אֶת־אֲמִתֵּנוּ": "term used to indicate a direct object-I-will-we had died",
 "כְּחָק־טִבְעָם": "as-enactment-to drown-them",
 "נִנָּצֵל": "we-will-snatch",
 "נְצַוֶּה": "we-will-constitute",
 "בְּכָל־הָאִגְּרוֹת": "among-all-the-letters",
 "בִּלְתִּי־צְבוּעָה": "except-painted",
 "בְּעִסְקֵי": "in-business",
 "גַּם־נִמְלֹךְ": "also-to consult (someone)",
 "וְאִם־נְכַחֶשׁ־בּוֹ": "and-whether?-we-will-it has become lean-in-it",
 "יַנִּיס": "he-will-Nice (French city)",
 "וּבָעִנּוּיִם": "and-in-the-humble people",
 "הַכְרֵז": "to be announced",
 "וְהַתְמֵד": "and-the-mead",
 "אֶל־הַהַגָּדוֹת": "at-the-Gad(pl)",
 "אֶת־שֵׁרוּתֶךָ": "term used to indicate a direct object-freedom",
 "לְדַלְמָטְיָה": "to-Dalmatia (also: Dalmacija)",
 "הַקְּלָף": "the-card",
 "בְּהִצְטַדְּקִי": "in-to justify oneself-my",
 "אֶל־גָּיוֹס": "at-enlistment",
 "וְעִם־הָאֹרְחִים": "and-equally with-the-travelers",
 "וּלְהוֹחִיל": "and-to-to wait",
 "וּבְשׁוֹמְרוֹן": "and-in-Samaria",
 "תְּחוּם": "area",
 "תְּהִי־טִירָתוֹ": "let it be-a battlement of-his",
 "וְהַשְּׁלִיחוּת": "and-the-mission",
 "לוּב": "Libya",
 "אֶת־הַנּוֹשָׁעִים": "term used to indicate a direct object-the-which it has been saved(pl)",
 "וּבַחֲסִידוּתֵנוּ": "and-in-the-Hassidism-our",
 "אֶת־הָאֲרֻכָה": "term used to indicate a direct object-the-healing",
 "וְגַם־מְפֻרְסָם": "and-assemblage-famous",
 "נִגְעֲרָה־בָּם": "we-will-a rebuke-them",
 "הִפָּטְרָם": "to be absolved-them",
 "אֶת־גַּעֲרָתָם": "term used to indicate a direct object-you have rebuked-them",
 "הוֹקִיר": "to respect",
 "אַךְ־צִלּוֹ": "but-shadow-his",
 "וְעַל־שִׁמּוּשׁ": "and-were from-use",
 "הִתְחַכֵּם": "to outsmart",
 "אֶתְמֹל": "I-will-yesterday",
 "נְכֵי": "we-will-that",
 "וּמַבְהִיל": "and-terrifying",
 "מַבְהִיל": "terrifying",
 "תִּסָּלַח": "you/she-will-to forgive",
 "עַל־כָּל־גְּנָזֶיהָ": "super- (superhuman, supernatural)-every-treasure-her",
 "גּוֹזְזֶיהָ": "sheep-shearer-her",
 "בְּקֵיסַרְיָה": "in-Caesarea (city)",
 "הָאִיטַלְקִי": "the-Italian (person)",
 "בְּהִתְפָּעֵם": "in-to be impressed",
 "בְּהוֹקִיעָם": "in-to denunciate-them",
 "נִשְׁפְּכָה": "we-will-penis",
 "וּמִשִּׂמְחָתָהּ": "and-from-the rejoicing of-her",
 "אֶת־הַשִּׁמּוּשׁ": "term used to indicate a direct object-the-use",
 "נִיגַר": "we-will-to fear",
 "שַׂר־הָרֹבַע": "the commander of-the-quarter",
 "תַּחְשְׁבוּנִי": "you/she-will-arithmetic",
 "וּלְסָקְלָם": "and-to-to stone-them",
 "וְדֶרְבִּי": "and-derby",
 "הִסְתַּכֵּל": "to look",
 "וּלְפוֹלוֹס": "and-to-Paul",
 "מִן־הַבְלֵיכֶם": "from-the-not-your(pl)",
 "לְהַחֲמִיר": "to-to worsen",
 "וּמְקַלְקְלִים": "and-broken(pl)",
 "חֲבִיבֵינוּ": "pleasant-our",
 "תְּפִילָּה": "you/she-will-elephant (female)",
 "אֶל־תַּסְלוֹנִיקִי": "at-you/she-will-Salonika",
 "גַּם־הֲלוֹם": "also-hither",
 "עִם־הַנִּקְרִים": "with-the-bore(pl)",
 "אַפִּיקוֹרוֹס": "heretic",
 "נִשְׁמָעֲךָ": "we-will-report-your",
 "נִפְטַר": "to die",
 "סוּדָרִים": "sweater(pl)",
 "נְבוֹנֵי": "we-will-Bunni",
 "הִמְצִיא": "to invent",
 "הָעֹסְקִים": "the-to deal with(pl)",
 "אֶת־גָּיוֹס": "term used to indicate a direct object-enlistment",
 "שֶׁל־הָאֶפֶסִים": "on account of-the-ankles",
 "נִדֹּנִים": "we-will-judging",
 "הַבְּרוֹאִי": "the-created-my",
 "הַדֶּרְבִּי": "the-derby",
 "כִּיּוֹס": "pickpocketing",
 "אֶל־קוֹס": "at-kvass",
 "אֶל־רוֹדוֹס": "at-Rhodes",
 "נְזִירוּת": "monasticism",
 "הַתִּגְלָחַת": "the-shave",
 "וּסְבוּרִים": "and-to be of the opinion that(pl)",
 "הַמְּסֻיָּד": "the-whitewashed",
 "וְלַחֲטֹף": "and-to-the-to grab",
 "לְהַרְכִּיב": "to-the-component",
 "בְּהַאֲמִינִי": "in-the-amino",
 "יְחַכּוּ־לָהּ": "he-will-adhere-belonged to-her",
 "קָרְבָּנוֹת": "victimhood",
 "הִצְטַדֵּק": "to justify oneself",
 "תִּשְׁמָעֶנּוּ": "you/she-will-listen to-us",
 "כָּל־הַמִּנְהָגִים": "every-the-driving(pl)",
 "הִמְרֵיתִי": "I have been rebellious",
 "לְהֵעָנוֹת": "to-response",
 "מִן־תַּסְלוֹנִיקִי": "from-you/she-will-Salonika",
 "הִנִּיחָנוּ": "to leave alone-our",
 "הַסַּכָּנָה": "the-danger",
 "נַחֲשֹׁל": "faltering",
 "לְטִלְטוּלֵנוּ": "to-movement-our",
 "מֵעַל־אֲחוֹרֵי": "above-rear",
 "פֶּן־יִשְׂחֶה": "lest-he-will-swim",
 "וְהַלֹּעֲזִים": "and-the-to write or speak in a foreign language(pl)",
 "עַל־הַמּוֹקֵד": "super- (superhuman, supernatural)-the-bonfire",
 "דְּרוֹמִית": "southward",
 "הַמְזַכֶּה": "the-credit",
 "וּנְמִיכוּת": "and-lowness",
 "מִן־הַמּוּלִים": "from-the-in front of(pl)",
 "מִן־הָעֹזְרִים": "from-the-to help(pl)",
 "הָרוֹפֵא": "the-doctor",
 "יְעָדָנוּ": "to designate-our",
 "הֶחֱיָנוּ": "living thing-our",
 "אַף־הוֹשִׁיבָנוּ": "also-cause them to dwell-our",
 "אֶכְרְעָה": "I-will-like-a shepherd",
 "מִכָּל־מִשְׁאֲלוֹתֵינוּ": "from-all-from-Sheol-our",
 "מֶה־הָרָצוּי": "what?-the-desirable",
 "מוֹקִירִים": "esteemer(pl)",
 "פְרִיצוּת": "immorality",
 "אִם־הִמָּלְאוּ": "if-they have been completed",
 "נִכְלֵי": "we-will-the articles of",
 "לְהַעְתִּיר": "to-the-rich",
 "כִּי־יְבַשֵׂר": "that-he-will-full",
 "אֲבַשְׂרֶנּוּ": "I-will-flesh-our",
 "כִּי־הָרֹדֵף": "that-the-is one who pursues",
 "וְהַנֶּחֱשָׁבִים": "and-the-it was reckoned(pl)",
 "אֶת־הָאֶבְיוֹנִים": "term used to indicate a direct object-the-needy people",
 "תַּכְרִיחַ": "you/she-will-is like-the smell of",
 "אֲבַטֵּל": "I-will-desist from labor",
 "מְשֻׁעְבָּדִים": "enslaved(pl)",
 "נָבוֹךְ": "embarrassed",
 "הַיּוֹלֶדֶת": "the-woman in confinement",
 "שִׁחֲרַר": "to be released",
 "נְיַחֵל": "we-will-he will violate",
 "הַפִּתּוּי": "the-temptation",
 "אִם־תְּנַשְּׁכוּ": "if-you/she-will-they will bite",
 "פֶּן־תְּכֻלּוּ": "lest-you/she-will-they have finished",
 "וּפְרִישׁוּת": "and-asceticism",
 "כִּי־נִקְצֹר": "that-to be reaped (grain)",
 "נִרְפֶּה": "lazy",
 "לְהִתְהַדֵּר": "to-you must show partiality",
 "וְלֹא־הָעָרְלָה": "and-no-the-foreskin",
 "אֶת־חַבּוּרוֹת": "term used to indicate a direct object-stub(pl)",
 "יְבַטֵּל": "he-will-desist from labor",
 "רַחֲמָן": "merciful",
 "הִתְקוֹטֵט": "to quarrel",
 "עַל־הַשֹּׁגֲגִים": "super- (superhuman, supernatural)-the-sin(pl)",
 "סַרְסוֹר": "pimp",
 "דִּמְיוֹנֵי": "imaginary",
 "בַּקָּרְבָּנוֹת": "in-the-victimhood",
 "בַּל־נִמּוֹט": "not-to collapse",
 "בְּהִשְׁתַּתֵּף": "in-to participate",
 "הַמַּקִּיף": "the-comprehensive",
 "אֶת־בְּכוֹרָתוֹ": "term used to indicate a direct object-in-beehive-his",
 "נִמְשָׁשׁ": "we-will-feel of",
 "תִּסָּקֵל": "you/she-will-to stone",
 "הַהַזָּאָה": "the-sprinkling",
 "אִם־נְמָאֵן": "if-we-will-are refusing",
 "נִרְעָשׁ": "flustered",
 "הָאִישׁוּת": "the-wedlock",
 "אֶת־מַנְהִיגֵיכֶם": "term used to indicate a direct object-leader-your(pl)",
 "נֵצְאָה־נָּא": "go away-please",
 "אֶל־מַנְהִיגֵיכֶם": "at-leader-your(pl)",
 "אֶת־הָרָצוּי": "term used to indicate a direct object-the-desirable",
 "כָּל־מַנְהִיגֵיכֶם": "every-leader-your(pl)",
 "אֶת־הָרֶסֶן": "term used to indicate a direct object-the-bridle",
 "כָּל־גְּוִיָּתָם": "every-the corpse of-them",
 "לְהוּטָה": "enthusiastic",
 "נְקַלֵּל": "we-will-curse",
 "הִשְׁכִּין": "to impose",
 "הִתְעַנּוּ": "you will afflict",
 "פְּלוֹנִית": "unidentified person (female)",
 "רֹאשׁ־הַמְּסִבָּה": "head-the-backside",
 "אֶת־הַגָּרוּעַ": "term used to indicate a direct object-the-bad",
 "וּפֹרְטֵי": "and-private",
 "תְּקִימֶנּוּ": "you/she-will-adversary-our",
 "הִגְבִּיהַּ": "to raise",
 "אֶטְעֹן": "I-will-to claim",
 "נִאוּפָהּ": "we-will-baker",
 "מִן־הַתַּחְתּוֹנִים": "from-the-underwear",
 "מִן־הָרוֹק": "from-the-rock music",
 "נִסְקֹל": "to be stoned (with stones)",
 "בֹּכִיָּה": "weeping",
 "אִם־תַּאֲמִינִי": "if-you/she-will-amino",
 "יִתְפְּשֹֻׁהוּ": "he-will-seize-him",
 "לֹא־נִמְכְּרָה": "no-he has sold himself",
 "נִמְשַׁךְ": "to be pulled",
 "יִנְצְרֶהָ": "he-will-keep watch-!",
 "וְהִשְׁמִין": "and-to become fat",
 "חָבִיב": "pleasant",
 "יְטַהֲרֶנּוּ": "he-will-we have cleansed",
 "יְפָאֶרְךְ": "he-will-he has glorified-you",
 "חוֹתֵן": "father-in-law",
 "הִמָּסֵר": "to give",
 "צְלֹב": "cross",
 "אֶצְלֹב": "I-will-cross",
 "וְרוֹמִית": "and-Latin (language)",
 "וְהַסּוּדָר": "and-the-sweater",
 "אֶת־טְלָאָי": "term used to indicate a direct object-patch",
 "תִּזְקַן": "you/she-will-old of",
 "עַל־מִיתָתוֹ": "super- (superhuman, supernatural)-from-Jetheth-his",
 "בַּסְּעוּדָה": "in-the-meal",
 "אֶל־הַמְקֹרָאִים": "at-the-biblical verse(pl)",
 "יְנָאֲצוּ": "he-will-they spurned",
 "בְּהִתְוַכְּחוֹ": "in-to argue-his",
 "מֵחָק־טִבְעָם": "from-enactment-to drown-them",
 "כֹּכָבִים": "to star(pl)",
 "מִן־הַצִּבּוּר": "from-the-public",
 "הִבָּנוּ": "they had built",
 "אֶל־הַחַזָּן": "at-the-cantor",
 "אֶת־מִכְמְרוֹתֵיכֶם": "term used to indicate a direct object-from-shrivel-your(pl)",
 "אֶל־חַבְרֵיהֶם": "at-to join (people)-their",
 "עַל־טָהֳרָתְךָ": "super- (superhuman, supernatural)-the purification-your",
 "לְהַכְנִיסוֹ": "to-to insert-his",
 "מִן־הַמּוֹכְסִים": "from-the-tax-collectors",
 "תְּחִנּוֹת": "you/she-will-vault",
 "יְחַבֵּב": "he-will-to love",
 "מַדְלִיק": "wonderful",
 "גָּנוּז": "hidden",
 "בַּזִּיקִים": "in-the-spark(pl)",
 "מִן־הָאֵבוּס": "from-the-stall",
 "כָּל־הַמּוֹכְסִים": "every-the-tax-collectors",
 "וּתְחַפֵּשׂ": "and-to dress someone in a costume",
 "אֶל־שְׂדוֹתָיו": "at-a breast-his",
 "מָה־הִרְוִיחַ": "what-to earn",
 "אֶל־הַשְּׂרָרָה": "at-the-authority",
 "אֶת־נִכְלֵיהֶם": "term used to indicate a direct object-act treacherously-their",
 "מִן־הַצַּדּוּקִים": "from-the-Zadok(pl)",
 "רָמַז": "to hint",
 "תּוֹאֲנָה": "pretext",
 "גַּם־אֶת־הַתַּרְמִיל": "also-term used to indicate a direct object-the-bag",
 "אֶת־מִכְמְרֹתֵיהֶם": "term used to indicate a direct object-net-their",
 "עִם־הַשְׂכִירִים": "with-the-a hired laborer of(pl)",
 "וְחוֹתֶנֶת": "and-mother-in-law",
 "נִגְנַז": "to be hidden",
 "מוֹדְדִים": "surveyor(pl)",
 "עַל־כָּל־הַיְרָקוֹת": "super- (superhuman, supernatural)-every-the-vegetables",
 "יְבָאֵר": "he-will-make it clear",
 "הַלִּגְיוֹן": "the-legion",
 "סַנְדָּל": "sandal",
 "הַמֻּכְשָׁר": "the-talented",
 "תַּחְפְּצִי": "you/she-will-pleasure",
 "הֵאִיץ": "to speed up",
 "תִּפָּלֵא": "you/she-will-distinguish",
 "וְאֶת־מוֹשְׁבוֹת": "and-hoe-dwelling(pl)",
 "הַהוֹרֵס": "the-wonderful",
 "וְגַם־הַנִּצְלָבִים": "and-assemblage-the-to be crucified(pl)",
 "וְשֶׁל־יוֹסֵי": "and-on account of-Yossi (Hebrew name)",
 "יוֹסֵי": "Yossi (Hebrew name)",
 "אֲשַׁלְּחֶנָּה": "I-will-table-her",
 "הַמּוֹכֵס": "the-customs official",
 "יִלָּחֵשׁ": "he-will-to whisper",
 "וְהַמְסֻבִּים": "and-the-around",
 "יִטְרְפֻהָ": "he-will-food ritually unfit for eating",
 "לַסְּעוּדָה": "to-the-meal",
 "קִטְּעִים": "section(pl)",
 "וְהַקִּטְּעִים": "and-the-section(pl)",
 "הַנִּשְׂכָּרִים": "the-to be hired(pl)",
 "פָּסַקְתָּ": "part",
 "אֶת־הַמְסֻבִּים": "term used to indicate a direct object-the-around",
 "יִרְטַב": "he-will-be moist",
 "עִם־הַסּוֹבְאִים": "with-the-become tipsy",
 "אֶתְכֶן": "I-will-measure",
 "הִרְוִיחַ": "to earn",
 "תִּתְחַזֵּק": "you/she-will-it will be too strong",
 "אֶנָּתֵן": "I-will-to give",
 "צְדָדִים": "to side with(pl)",
 "הִגְבִּיהוֹ": "to raise-his",
 "לְחִזּוּק": "to-strengthening",
 "מִן־הַחִתּוּךְ": "from-the-cutting",
 "וּמִתְפָּאֲרִים": "and-from-you will go over the boughs(pl)",
 "לְהַרְוִיחַ": "to-to earn",
 "וּלְהִדַּמּוֹת": "and-to-modeling oneself on",
 "אֶזְרָחוּתֵנוּ": "citizenship-our",
 "הַנִּצְמָד־לִי": "the-to stick to-for-me",
 "יִנְצֹר": "he-will-keep",
 "וְגַם־מַשְׁגִּיחִים": "and-assemblage-is gazing(pl)",
 "לְהִסְתַּפֵּק": "to-to be satisfied with",
 "בְּהִתְחַבֶּרְכֶם": "in-to fit together-your(pl)",
 "לֹא־הִתְחַבְּרָה": "no-to fit together",
 "נִמְלֵאתִי": "we-will-I filled",
 "פּוֹשֵׁר": "lukewarm",
 "תִּשְׁקֹד": "you/she-will-keeping watch",
 "יְנַצֵּחַ": "he-will-act as overseers",
 "נִגְלָל": "to be rolled up",
 "אַל־תְּחַבְּלוּ": "Don't!-you/she-will-rope-his",
 "וְהָשְׁלְטוּ": "and-the-they domineered",
 "שָׁהוּת": "time",
 "אֲשֶׁר־נִרְפְּאָה": "which-it has been healed",
 "עַל־מִצְחֹתָם": "super- (superhuman, supernatural)-leg armor of-them",
 "נִקְנוּ": "we-will-nest-its",
 "נִקְצָרָה": "to be reaped (grain)",
 "יִירָאֲךָ": "he-will-will he fear-you",
 "אֱזוֹרֵי": "regional",
 "נֶחְלְקָה": "to be divided",
 "הַמּוּבָן": "the-clear",
 "וּמִַצְהִיר": "and-declarant",
 "מַבְהִיק": "radiant",
 "וּשְׁלִיחוּת": "and-mission",
 "וּלְהַאֲצִיל": "and-to-to delegate authority",
 "וְלַלּעֲזִים": "and-to-the-to write or speak in a foreign language(pl)",
 "נְדָבַנִי": "philanthropic",
 "אֶת־חֲבֵרְךָ": "term used to indicate a direct object-to join (people)-your",
 "תְּחַיֵּב": "insert (in magazine, newspaper etc.)",
 "וּלְחֶמְלָתוֹ": "and-to-you have spared-his",
 "תְּשַׁקֵּץ": "you/she-will-utterly",
 "לֹא־הַמְצֻיָּן": "no-the-excellent",
 "עֲמִידָה": "standing",
 "דְּבוּקִים": "firmly attached(pl)",
 "אִם־לַמִּשְׁמַעַת": "if-to-the-court",
 "מְשֻׁחֲרָרִים": "liberator(pl)",
 "וּמְשֻׁעְבָּדִים": "and-enslaved(pl)",
 "הִתְנַגְּפוּ": "you will be defeated",
 "הֲזָנַח": "to be neglected",
 "הָעִסָּה": "the-dough",
 "אַל־תִּתְפָּאֵר": "Don't!-you/she-will-you will go over the boughs",
 "וְאִם־תִּתְפָּאֵר": "and-whether?-you/she-will-you will go over the boughs",
 "לְהַרְכִּיבָם": "to-the-component-them",
 "נִגְזַרְתָּ": "derivative",
 "טִמְטוּם": "stupidity",
 "שִׁמּוּשׁ": "use",
 "וְאִם־שִׁמּוּשׁ": "and-whether?-use",
 "בְּשִׁמּוּשׁוֹ": "in-use-his",
 "בְּסֵבֶר": "in-facial expression",
 "לְהַכְנִיס": "to-to insert",
 "אַל־תְּהַלְּכוּ": "Don't!-you/she-will-went",
 "אַל־תִּנָּקְמוּ": "Don't!-you/she-will-they have avenged themselves",
 "נְכוֹנֵן": "we-will-give attention",
 "אַל־תַּהֲרוֹס": "Don't!-you/she-will-tear down",
 "תֶּעְדַּף": "to prioritize",
 "בְּהִשְׁתַּדְּלִי": "in-to make efforts-my",
 "וְאַף־מְחֻיָּבִים": "and-nose-obligated(pl)",
 "בְּהַעְתִּירְכֶם": "in-the-rich-your(pl)",
 "אֶנָּצֵל": "I-will-snatch",
 "שִׁמּוּשִׁי": "useful",
 "גָּיוֹס": "enlistment",
 "הַמְאָרֵחַ": "the-host",
 "לַחֲסִידוּת": "to-the-Hassidism",
 "טַעֲנַת": "load (river)",
 "פְּרִיצוּת": "immorality",
 "כִּי־הֶגְמוֹן": "that-bishop",
 "וְצָנוּעַ": "and-modest",
 "מִן־הַנִּמּוֹלִים": "from-the-circumcised(pl)",
 "סָכוֹר": "dammed",
 "בְּהוֹרוֹתָם": "in-parenthood-them",
 "אֶל־הַגָּדוֹת": "at-the-Gad(pl)",
 "אֶת־הַנָּאֶה": "term used to indicate a direct object-the-home",
 "אִם־מְלַמְּדוֹת": "if-goad(pl)",
 "אֶת־הַצְּעִירוֹת": "term used to indicate a direct object-the-youth",
 "צְנוּעוֹת": "modest(pl)",
 "תַּזְהִיר": "you/she-will-careful",
 "הַזָּרִיז": "the-quick",
 "וְחִדּוּשׁ": "and-innovation",
 "אֶת־הַמְּצוּרוֹת": "term used to indicate a direct object-the-siege(pl)",
 "לֹא־נַמְלִךְ": "no-to consult (someone)",
 "אֶת־מִזְבְּחֹתָו": "term used to indicate a direct object-altar",
 "אֲשֶׁר־הֶחֱטִי": "which-miss",
 "אֶת־פַּת־בָּגָם": "term used to indicate a direct object-a morsel of-in-the-also",
 "כׇל־דִּי־יִבְעֵא": "all-which-he-will-he asked",
 "דִּי־יִבְעֵא": "which-he-will-he asked",
 "וְהַלְּבָנֹן": "and-the-sponge cake",
 "אֲרִידַי": "arid",
 "וְהִפִּל": "and-to be knocked over",
 "כֵּסְיָהּ": "xi (the fourteenth letter of the Greek alphabet)-her",
 "אוֹ־ֶת־עֵין": "or-Tav (twenty-second (last) letter in Hebrew alphabe-En",
 "ֶת־הַנְּפָשׁוֹת": "Tav (twenty-second (last) letter in Hebrew alphabe-the-persons",
 "פֹּרֹאות": "recklessness",
 "בְּרַגְֵיכֶם": "screw (noun)-your(pl)",
 "וּמֵהַתִּכוֹנוֹת": "and-from-intending",
 "וְכׇל־תּוֹרֹתָו": "and-all-custom",
 "וּלְכׇל־תּוֹרֹתָו": "and-to-all-custom",
 "אֳנִיֹּת": "lobule",
 "יְסַכֵּל": "he-will-be silly",
 "סִיחוֹ": "foal-his",
 "יְִיֶה": "he-will-Yahweh",
 "יִלְטֹשׁ": "he-will-to sharpen",
 "תְּבֹאֶנּוּ": "you/she-will-we went",
 "תִּקֹּב": "you/she-will-crutch",
 "וְכׇל־אַחְיֹתָיו": "and-all-sister",
 "אֶל־הָאֱלִילִם": "at-the-worthless idols",
 "כׇּל־נִדְבֹתֵיכֶם": "all-a freewill offering of-your(pl)",
 "יְמִתֶנּוּ": "he-will-we had died",
 "שַׁעֲשׁוּעִים": "entertainment(pl)",
 "תְּעֹרֵר": "you/she-will-to rouse",
 "וְגוֹלֵל": "and-to wind",
 "אֶל־אֲדֹנָו": "at-controller",
 "הִתְרוֹעָעִי": "to befriend-my",
 "לְהִסָּמֵךְ": "to-to depend on",
 "אֶת־מִנּוּיִי": "term used to indicate a direct object-from-beauty-my",
 "כְּמִנּוּי": "as-appointing",
 "אֶת־הַסֵּדֶר": "term used to indicate a direct object-the-order",
 "מִן־הַשּׁוּשֶׁלֶת": "from-the-dynasty",
 "אִטִּי": "slow",
 "כָּל־הַמְּאוֹרוֹת": "every-the-lighting(pl)",
 "אֶת־הַשְּׂכָלִים": "term used to indicate a direct object-the-childlessness",
 "נִיצֹר": "we-will-to create",
 "שֶׁתֻּרְגַּם": "that-translate",
 "בְּהִכָּנְעוּת": "in-surrendering",
 "וְהִתְקַדְּמוּתָהּ": "and-advance-her",
 "וּבְהִתְקַדְּמוּתָהּ": "and-in-advance-her",
 "שֶׁרִגְשׁוֹתֵיהֶם": "that-to be stormy-their",
 "רִגְשׁוֹתֵיהֶם": "to be stormy-their",
 "וּבְוִכּוּחַ": "and-in-discussion",
 "לְמַסְקָנָה": "to-conclusion",
 "הִתְרַגֵּשׁ": "to be excited",
 "וּלְהַפְרִיךְ": "and-to-to refute",
 "שֶׁנִּגְרַם": "that-to be caused",
 "שֶׁנִּכְנַס": "that-to enter",
 "בְּהַסִּיקִי": "in-the-Sikh (person)",
 "בְּיֵאוּשׁ": "in-despair",
 "בְּהַצְבִּיעָהּ": "in-the-painting",
 "שֶׁכֻּלָּן": "that-everyone (female)",
 "הִתְנַהֲגוּתוֹ": "behavior-his",
 "הִתְיַחֵס": "to relate to",
 "שֶׁסִּפּוּרִי": "that-narrative",
 "נְשִׁימָתוֹ": "we-will-that-they will die",
 "הָרְגִילוֹת": "the-regular(pl)",
 "וּלְהִתְיַחֵס": "and-to-to relate to",
 "לְפִתּוּיִים": "to-temptation(pl)",
 "מְהַוּוֹת": "what is?(pl)",
 "שֶׁבָּרְחָה": "that-he fled",
 "מֵהַשְׁתָּאוּת": "from-amazement",
 "מְחַזֵּר": "returned",
 "לְהֻשְׁפַּע": "to-to be influenced",
 "מִמָּנִיעַ": "from-motivation",
 "שֶׁשִּׂיחוֹתֵינוּ": "that-shrub of-our",
 "יִפְגֹּשׁ": "he-will-come in",
 "שֶׁנְּסִיבוֹת": "that-circumstances",
 "לְהִשְׂתַּכֵּר": "to-to earn",
 "שֶׁנִּשְׂכַּרְתִּי": "that-I-was-hired",
 "הָרוֹוֵחַ": "the-common",
 "נִשּׂוּאַי": "predicative",
 "בְּרַשְׁלָנוּת": "in-negligence",
 "מִזְּנִיחָה": "from-abandonment",
 "קְפֵדָנִיּוֹת": "meticulous(pl)",
 "נִסְבֶּלֶת": "we-will-Sibboleth",
 "שֶׁנֶּאֱלַצְתִּי": "that-I-was-forced",
 "בְּהִתְכּוֹנְנוּתֵנוּ": "in-preparing oneself-our",
 "עִירִיַּת": "chives",
 "וּבְאֶמְצָעוּת": "and-by means of",
 "מִתִּישֶׁהוּ": "whenever",
 "מְפֹאָר": "magnificent",
 "שֶׁהַתִּרְגּוּם": "that-the-translation",
 "וְכַשְׂדִּית": "and-Chaldee",
 "וְאַשּׁוּרִית": "and-Assyrian (language)",
 "בַחֲזָרָה": "on the way back",
 "לַדּוֹקְטוֹר": "to-the-Dr",
 "בַּשְּׁכוּנָה": "in-the-neighborhood",
 "לְהִתְאַכְסֵן": "to-to be housed",
 "וּלְפִיכָךְ": "and-therefore",
 "הַמַּשְׁמָעוּת": "the-meaning",
 "וְהַכַּוָּנָה": "and-the-intention",
 "הֲגָנָה": "defense",
 "תִּקְרַר": "you/she-will-to cool",
 "אַל־תִּבָּהֲלוּ": "Don't!-you/she-will-when-made shine-he",
 "תָּקֵר": "puncture",
 "וְתֵכֶף": "and-in a moment",
 "חֵנִי": "station",
 "וּנְשׁוֹתֵינוּ": "and-man-our"
}