[{"pk":3171466,"verse":1,"text":"עַל־כֵּן עַתָּה אֵין־אַשְׁמָה בָאֵלֶּה אֲשֶׁר הֵם בַּמָּשִׁיחַ יֵשׁוּעַ הַמִּתְהַלְּכִים שֶׁלּא כַבָּשָׂר אֶלָּא לְפִי הָרוּחַ׃"},{"pk":3171467,"verse":2,"text":"כִּי תוֹרַת רוּחַ הַחַיִּים אֲשֶׁר בַּמָּשִׁיחַ יֵשׁוּעַ הוֹצִיאָה אֹתִי לַחָפְשִׁי מִתּוֹרַת הַחֵטְא וְהַמָּוֶת׃"},{"pk":3171468,"verse":3,"text":"כִּי מַה־שֶּׁלּא יָכְלָה הַתּוֹרָה לַעֲשׂוֹת מִפְּנֵי שֶׁנֶּחֱלַשׁ כֹּחָהּ עַל־יְדֵי הַבָּשָׂר אֹתוֹ עָשָׂה הָאֱלֹהִים בְּשָׁלְחוֹ אֶת־בְּנוֹ בְּדִמְיוֹן בְּשָׂר הַחֵטְא וּבְעַד הַחֵטְא וַיַּרְשִׁיעַ אֶת־הַחֵטְא בַּבָּשָׂר׃"},{"pk":3171469,"verse":4,"text":"כְּדֵי שֶׁתְּקֻיַּם צִדְקַת הַתּוֹרָה בָּנוּ הַהֹלְכִים לֹא־כְדֶרֶךְ הַבָּשָׂר כִּי אִם־לְפִי הָרוּחַ׃"},{"pk":3171470,"verse":5,"text":"כִּי בְּנֵי הַבָּשָׂר יֶהְגּוּ בְּדִבְרֵי הַבָּשָׂר וּבְנֵי הָרוּחַ בְּדִבְרֵי הָרוּחַ׃"},{"pk":3171471,"verse":6,"text":"כִּי־מַחֲשֶׁבֶת הַבָּשָׂר הִיא הַמָּוֶת וּמַחֲשֶׁבֶת הָרוּחַ הִיא הַחַיִּים וְהַשָּׁלוֹם׃"},{"pk":3171472,"verse":7,"text":"מִפְּנֵי שֶׁמַּחֲשֶׁבֶת הַבָּשָׂר רַק שִׂנְאַת אֱלֹהִים הִיא בַּאֲשֶׁר לֹא תִשְׁתַּעְבֵּד לְתוֹרַת הָאֱלֹהִים וְאַף לֹא תוּכָל׃"},{"pk":3171473,"verse":8,"text":"כָּל־אֲשֶׁר בַּבָּשָׂר יְסוֹדָם לֹא יוּכְלוּ לִהְיוֹת רְצוּיִם לֵאלֹהִים׃"},{"pk":3171474,"verse":9,"text":"וְאַתֶּם אֵינְכֶם בַּבָּשָׂר כִּי אִם־בָּרוּחַ אִם־אָמְנָם רוּחַ הָאֱלֹהִים שֹׁכֵן בְּקִרְבְּכֶם כִּי מִי שֶׁאֵין־בּוֹ רוּחַ הַמָּשִׁיחַ הוּא אֵינֶנּוּ שֶׁלּוֹ׃"},{"pk":3171475,"verse":10,"text":"וְאִם־הַמָּשִׁיחַ בְּקִרְבְּכֶם הַגּוּף מֵת בִּגְלַל הַחֵטְא וְהָרוּחַ חַיִּים בִּגְלַל הַצְּדָקָה׃"},{"pk":3171476,"verse":11,"text":"וְאִם־יִשְׁכֹּן בְּקִרְבְּכֶם רוּחוֹ שֶׁל הַמֵּעִיר אֶת־יֵשׁוּעַ מִן־הַמֵּתִים הַמֵּעִיר אֶת־הַמָּשִׁיחַ מִן־הַמֵּתִים הוּא גַם אֶת־גְּוִיּוֹתֵיכֶם הַמֵּתוֹת יְחַיֶּה עַל־יְדֵי רוּחוֹ הַשֹּׁכֵן בְּקִרְבְּכֶם׃"},{"pk":3171477,"verse":12,"text":"לָכֵן אַחַי חַיָּבִים אֲנַחְנוּ לֹא לַבָּשָׂר לִחְיוֹת לְפִי הַבָּשָׂר׃"},{"pk":3171478,"verse":13,"text":"כִּי אִם־תִּחְיוּ לְפִי הַבָּשָׂר מוֹת תְּמֻתוּן וְאִם־עַל־יְדֵי הָרוּחַ תָּמִיתוּ אֶת־מַעַלְלֵי הַבָּשָׂר חָיֹה תִחְיוּ׃"},{"pk":3171479,"verse":14,"text":"כִּי־כֹל אֲשֶׁר רוּחַ אֱלֹהִים יְנַהֲגֵם בְּנֵי אֱלֹהִים הֵמָּה׃"},{"pk":3171480,"verse":15,"text":"כִּי לֹא קִבַּלְתֶּם רוּחַ עַבְדוּת לָשׁוּב לִירֹא כִּי אִם־קִבַּלְתֶּם רוּחַ מִשְׁפַּט בָּנִים אֲשֶׁר בּוֹ קֹרְאִים אֲנַחְנוּ אַבָּא אָבִינוּ׃"},{"pk":3171481,"verse":16,"text":"וְהָרוּחַ הַהוּא מֵעִיד בְּרוּחֵנוּ כִּי־בְנֵי אֱלֹהִים אֲנָחְנוּ׃"},{"pk":3171482,"verse":17,"text":"וְאִם־בָּנִים אֲנַחְנוּ גַּם־יֹרְשִׁים נִהְיֶה יֹרְשֵׁי נַחֲלַת אֱלֹהִים וְחַבְרֵי הַמָּשִׁיחַ בִּירֻשָּׁה אִם־נִתְעַנֶּה אִתּוֹ לְמַעַן גַּם־אִתּוֹ נְכֻבָּד׃"},{"pk":3171483,"verse":18,"text":"כִּי אֹמֵר אֲנִי שֶׁעִנּוּיֵי הַזְּמַן הַזֶּה אֵינָם שְׁקוּלִים כְּנֶגֶד הַכָּבוֹד הַבָּא לְהִגָּלוֹת עָלֵינוּ׃"},{"pk":3171484,"verse":19,"text":"כִּי הַבְּרִיאָה תַּעֲרֹג וּתְצַפֶּה לַמּוֹעֵד אֲשֶׁר יִתְגַּלּוּ בְּנֵי הָאֱלֹהִים׃"},{"pk":3171485,"verse":20,"text":"כִּי־נִכְנְעָה הַבְּרִיאָה לַהֶבֶל לֹא מֵרְצוֹנָהּ כִּי אִם־לְמַעַן הַמַּכְנִיעַ אֹתָהּ וְלֹא בְּאֵין תִּקְוָה׃"},{"pk":3171486,"verse":21,"text":"כִּי הַבְּרִיאָה גַּם־הִיא תֵצֵא מֵעַבְדוּת הַכִּלָּיוֹן אֶל־חֵרוּת כְּבוֹד בְּנֵי הָאֱלֹהִים׃"},{"pk":3171487,"verse":22,"text":"כִּי יָדַעְנוּ אֲשֶׁר הַבְּרִיאָה כֻלָּהּ תֵּאָנַח וְתָחִיל עַד־הֵנָּה׃"},{"pk":3171488,"verse":23,"text":"וְלֹא־עוֹד אֶלָּא שֶׁגַּם־אֲנַחְנוּ אַף עַל פִּי שֶׁיֶּשׁ־לָנוּ בִּכּוּרֵי הָרוּחַ נֵאָנַח בְּנַפְשֵׁנוּ וּנְחַכֶּה לְמִשְׁפַּט הַבָּנִים לִפְדוּת גְּוִיָּתֵנוּ׃"},{"pk":3171489,"verse":24,"text":"כִּי נוֹשַׁעְנוּ בַתִּקְוָה אֲבָל הַתִּקְוָה הַנִּרְאָה לָעֵינַיִם אֵינֶנָּה תִקְוָה כִּי אֵיךְ יְיַחֵל אִישׁ לַדָּבָר אֲשֶׁר־הוּא רֹאֶה׃"},{"pk":3171490,"verse":25,"text":"אֶלָּא אִם־נְקַוֶּה לְמַה־שֶּׁלּא רְאִינֻהוּ נְחַכֶּה לוֹ וְנוֹחִיל׃"},{"pk":3171491,"verse":26,"text":"וְכֵן גַּם־הָרוּחַ תֹּמֵךְ אֹתָנוּ בְּחֻלְשׁוּתֵינוּ כִּי לֹא יָדַעְנוּ לְהִתְפַּלֵּל כָּרָאוּי אָכֵן הָרוּחַ הוּא מַפְגִּיעַ בַּעֲדֵנוּ בַּאֲנָחוֹת עֲמֻקּוֹת מִדַּבֵּר׃"},{"pk":3171492,"verse":27,"text":"וְהַחֹקֵר לְבָבוֹת יוֹדֵעַ אֶת־מַחְשְׁבוֹת הָרוּחַ כִּי כִּרְצוֹן הָאֱלֹהִים יַפְגִּיעַ בְּעַד הַקְּדוֹשִׁים׃"},{"pk":3171493,"verse":28,"text":"וְהִנֵּה יָדַעְנוּ כִּי אֹהֲבֵי אֱלֹהִים הַקְּרוּאִים בַּעֲצָתוֹ הַכֹּל יַעֲזֹר לְטוֹב לָהֶם׃"},{"pk":3171494,"verse":29,"text":"כִּי אֵת אֲשֶׁר יְדָעָם מִקֶּדֶם אֹתָם גַּם־יָעַד לִהְיוֹת דּוֹמִים לְצֶלֶם בְּנוֹ לְמַעַן יִהְיֶה הַבְּכוֹר בְּתוֹךְ אַחִים רַבִּים׃"},{"pk":3171495,"verse":30,"text":"וְאֶת אֲשֶׁר־יָעַד מִקֶּדֶם אֹתָם גַּם־קָרָא וְאֶת־אֲשֶׁר קָרָא אֹתָם גַּם־הִצְדִיק וְאֵת אֲשֶׁר הִצְדִּיק אֹתָם גַּם פֵּאֵר׃"},{"pk":3171496,"verse":31,"text":"וְעַתָּה מַה־נֹּאמַר עַל־זֹאת אִם־הָאֱלֹהִים לָנוּ מִי יָרִיב אִתָּנוּ׃"},{"pk":3171497,"verse":32,"text":"אֲשֶׁר־עַל־בְּנוֹ שֶׁלּוֹ לֹא חָס כִּי אִם־נְתָנוֹ בְּעַד כֻּלָּנוּ הֲלֹא יִתֵּן לָנוּ עִמּוֹ אֶת־הַכֹּל׃"},{"pk":3171498,"verse":33,"text":"מִי יַעֲנֶה בִּבְחִירֵי אֱלֹהִים הֵן אֱלֹהִים הוּא הַמַּצְדִּיק׃"},{"pk":3171499,"verse":34,"text":"וּמִי־הוּא יַאֲשִׁימֵם הֵן הַמָּשִׁיחַ אֲשֶׁר מֵת וַאֲשֶׁר נֵעוֹר מֵעִם הַמֵּתִים הוּא מִימִין הָאֱלֹהִים וְהוּא יַפְגִּיעַ בַּעֲדֵנוּ׃"},{"pk":3171500,"verse":35,"text":"מִי יַפְרִידֵנוּ מֵאַהֲבַת הָאֱלֹהִים הֲצָרָה אוֹ מְצוּקָה אוֹ מַשְׂטֵמָה אוֹ רָעָב אִם־עֶרְיָה אוֹ סַכָּנָה אוֹ־חָרֶב׃"},{"pk":3171501,"verse":36,"text":"כַּכָּתוּב כִּי־עָלֶיךָ הֹרַגְנוּ כָל־הַיּוֹם נֶחְשַׁבְנוּ כְּצֹאן טִבְחָה׃"},{"pk":3171502,"verse":37,"text":"אֲבָל בְּכָל־אֵלֶּה גָּבַרְנוּ מְאֹד עַל־יְדֵי הָאֹהֵב אֹתָנוּ׃"},{"pk":3171503,"verse":38,"text":"וּבָטוּחַ אֲנִי שֶׁלּא הַמָּוֶת וְלֹא הַחַיִּים לֹא מַלְאָכִים וְלֹא שְׂרָרוֹת וְלֹא גְבוּרוֹת לֹא הַהוֶֹה וְלֹא הֶעָתִיד׃"},{"pk":3171504,"verse":39,"text":"לֹא הָרוֹם וְלֹא הָעֹמֶק וְלֹא כָל־בְּרִיָּה יוּכְלוּ לְהַפְרִידֵנוּ מֵאַהֲבַת הָאֱלֹהִים אֲשֶׁר הִיא בַּמָּשִׁיחַ יֵשׁוּעַ אֲדֹנֵינוּ׃"}]